Workbook

Sheet Sheet1
A1: Dataset Title | B1: Short Description | C1: Category | D1: Keywords | E1: Type | F1: License Type | G1: Data Provider | H1: Data Provided by | I1: Source Link | J1: State Steward | K1: Citation | L1: Agency Program Page | M1: Agency Data Series Page | N1: Business Contact and Phone | O1: Technical Contact and Phone | P1: Data Source | Q1: Unit of Analysis | R1: Granularity Coverage | S1: Geographic Extent and Division | T1: Collection Mode | U1: Collection Methodology | V1: Data Collection Instrument | W1: Date of Initial Dataset Creation | X1: Field Names, comma delimited | Y1: Oldest Record in Dataset | Z1: Newest Record in Dataset | AA1: Long Description | AB1: Data Dictionary | AC1: Additional Metadata | AD1: Technical Documentation | AE1: Data Quality Certification | AF1: Applicable Information Quality Guideline Designation | AG1: Stewardship Plan | AH1: Collection Method | AI1: Horizontal Accuracy | AJ1: Horizontal Coordinate System | AK1: Update Schedule | AL1: Update Method | AM1: Source Update Schedule | AN1: Update Schedule Last Audit | AO1: Update Type | AP1: Total Records at Initial Publish | AQ1: Row Class RDF | AR1: Subject Column RDF | AS1: Single Row | AT1: Row Count (11/20/17) | AU1: Total Fields at Initial Publish | AV1: FIle Size at Initial Publish or as of 3-1-2016 | AW1: Expected approximate increase in record count at update | AX1: Date Published to CIM | AY1: GoCode FY Published to CIM | AZ1: Socrata Link | BA1: API 4x4 | BB1: MapViz | BC1: Web Display Coordinate System | BD1: Coordinate System Disclaimer | BE1: Related Datasets | BF1: Quarter of Gov FY Published | BG1: cimAllData Updates | BH1: Complexity | BI1: Business Contact Information - Name | BJ1: Business Contact Information - Position | BK1: Business Contact Information - Phone Number | BL1: Business Contact Information - Email | BM1: Technical Contact Information - Name | BN1: Technical Contact Information - Position | BO1: Technical Contact Information - Phone Number | BP1: Technical Contact Information - Email | BQ1: Name of Person Providing Data | BR1: Email of Person Providing Data
A2: Bill Information and Position with Income of Lobbyist in Colorado | B2: Information for each lobbyist and their associated client with the reported bills and positions associated with the client and the total gross income the client paid to lobbyist for the report month for the State of Colorado provided by the Colorado Department of State (CDOS). | C2: Lobbyist | D2: bic, gocodecolorado, colorado, sos, secretary of state, lobbyists, clients, bills, position on bill, income, gross income | E2: Bills | F2: Public Domain | G2: CDOS | H2: =IFERROR(G2&" - "&INDEX(Taxonomy!N:N,MATCH(G2,Taxonomy!M:M,0)),G2) -> CDOS | J2: CDOS | K2: =IFERROR(J2&" - "&INDEX(Taxonomy!N:N,MATCH(J2,Taxonomy!M:M,0)), J2) -> CDOS | L2: https://www.sos.state.co.us/ | M2: https://www.sos.state.co.us/pubs/lobby/FAQs/professional.html | N2: not public | O2: not public | Q2: Tabular | S2: State | X2: lobbyistlastname, lobbyistfirstname, lobbyistaddress0, lobbyistaddress1, lobbyistcity, lobbyiststate, lobbyistzip, primarylobbyistid, annuallobbyistregistrationid, officialstatelobbyist, clientname, clientlastname, clientfirstname, clientmiddlename, clientsuffix, clientaddress0, clientaddress1, clientcity, clientstate, clientzip, billinformationandposition, reportmonth, fiscalyear, reportduedate, clientbusinessdescription, clienttypeofbusiness, clientstatus, clientstartdate, clientenddate, incomeamount, dateincomereceived | Y2: 02/15/2016 | Z2: 11/15/2017 | AA2: The primaryLobbyistID field is the number is assigned when the lobbyist registers with the state, and the first four numbers are the year of original registration. The annual lobbyist registration identification number is updated when they register in a current fiscal year, and the first four numbers reflect status of the lobbyist when registering in a current fiscal year (for example, if they were registered in 2015, but did not update their registration in 2016, then the registration id would remain 2015 until they register in a new fiscal year). The data is updated as necessary to the main lobbyist online system via manual entry, however the updates to the Colorado Information Marketplace is only done weekly, every Monday night. Data goes back to 1995, but in 2002 a mandate established that the secretary of state transition to an online system. Then in 2010 Senate Bill 10-87, among other major changes, shifted the lobbyist registration and disclosure periods to the state fiscal year rather than the calendar year. Multiple bills are associated with a single monetary transaction (gross income) for a given month from a client to a lobbyist, and they are listed in the billInformationAndPosition field along with the position of the client. In a reporting month, income is reported based on the date that it is actually received. For example, in the event that a payment is made cumulatively over a three month period, they must report the full three month payment, and associated bills, when the payment was received. If a lobbyist has multiple payments received by various clients, each dollar amount is reported separately by each client. The statute specifies that lobbyists report the total amount they receive from the client. This is how the data is collected, and based on this database structure individual amounts associated with individual bills cannot be reported separately. State Liaisons are not required to report their position on the bill, only the legislation on which the lobbying is being performed. | AK2: =IF(AO2="Static", "None", IF(AO2="Manual - monthly", "4th of month", IF(AO2="Automated - weekly", "Tuesday after 12AM", IF(AO2="Automated - monthly", "4th of month", IF(AO2="Manual - annual", "Annually", IF(AO2="Automated - broken", "Automation in progress", IF(AO2="Automated - daily", "Every day after midnight", ""))))))) -> None | AL2: =IF(AO2="Static", "None", IF(AO2="Manual - monthly", "Manual", IF(AO2="Automated - weekly", "Automated by Staging Server", IF(AO2="Automated - monthly", "Automated by Staging Server", IF(AO2="Manual - annual", "Manual", IF(AO2="Automated - broken", "Automated by Staging Server", IF(AO2="Automated - daily", "Automated by Staging Server", ""))))))) -> None | AO2: Static | AS2: Lobbyist and client name, contact, information/position on bill, income received, and date income was received | AT2: 54140 | AX2: 42547 | AY2: =IF(DATEVALUE(AX2) < DATE(2014,7,1), 1, IF(DATEVALUE(AX2)<DATE(2015,7,1),2,IF(DATEVALUE(AX2)<DATE(2016,7,1),3,IF(DATEVALUE(AX2)<DATE(2017,7,1),4,IF(DATEVALUE(AX2)<DATE(2018,7,1),5,IF(DATEVALUE(AX2)<DATE(2019,7,1),6,IF(DATEVALUE(AX2) < DATE(2020,7,1), 7, IF(DATEVALUE(AX2) < DATE(2021,7,1), 8, IF(DATEVALUE(AX2) < DATE(2022,7,1), 9, IF(DATEVALUE(AX2) < DATE(2023,7,1), 10, IF(DATEVALUE(AX2) < DATE(2024,7,1), 11,IF(DATEVALUE(AX2) < DATE(2025,7,1),12,0)))))))))))) -> 3 | AZ2: =HYPERLINK("https://data.colorado.gov/Legislative/Bill-Information-and-Position-with-Income-of-Lobby/gxnn-wthy","gxnn-wthy") -> gxnn-wthy | BA2: =HYPERLINK("https://data.colorado.gov/resource/a2bk-zr8i.json","a2bk-zr8i") -> a2bk-zr8i | BE2: Joinable to: Characterization of Lobbyist Clients in Colorado, Directory of Lobbyist Clients in Colorado, Directory of Lobbyists in Colorado, Expenses for Lobbyists in Colorado, Subcontractors for Lobbyists in Colorado based on "primaryLobbyistId" | BF2: =IF(AND(MONTH(AX2)>=7,MONTH(AX2)<=9), 1, IF(AND(MONTH(AX2)>=9,MONTH(AX2)<=12), 2, IF(AND(MONTH(AX2)>=1,MONTH(AX2)<=3), 3, IF(AND(MONTH(AX2)>=4,MONTH(AX2)<=6), 4)))) -> 4 | BG2: =LEFT(XLOOKUP(AZ2, cimAllData!$B$2:B1001, cimAllData!$F$2:$F1001), 10) -> #REF! | BJ2: BIC Program Manager | BM2: Angela Lawson | BN2: Lobbyist Registration Program Manager | BO2: 303-894-2200, ext. 6304 | BP2: a.lawson@sos.state.co.us | BQ2: Sebbie Coleman | BR2: sebbie.coleman@sos.state.co.us
A3: Census Zip Codes in Colorado 2016 | B3: American Community Survey Census data includes demographics, education level, commute information, and more subset to Colorado by the Department of Local Affairs (DOLA). | C3: Demographics | D3: bic, gocodecolorado, colorado, census, zip codes, american community survey, location, geospatial, gis | E3: Census | F3: Public Domain | G3: DOLA | H3: =IFERROR(G3&" - "&INDEX(Taxonomy!N:N,MATCH(G3,Taxonomy!M:M,0)),G3) -> DOLA | I3: https://www2.census.gov/geo/tiger/TIGER_DP/2016ACS/ACS_2016_5YR_ZCTA.gdb.zip | J3: DOLA | K3: =IFERROR(J3&" - "&INDEX(Taxonomy!N:N,MATCH(J3,Taxonomy!M:M,0)), J3) -> DOLA | L3: https://www.colorado.gov/dola | M3: https://www.census.gov/geo/maps-data/ | N3: not public | O3: not public | Q3: Vector polygon | S3: State | T3: TIGER line files | U3: The 2000 census marked the last year that the long form was distributed to 1 in 6 households (a 17% sample), and in 2010 the actual sample size for the long form was 2.5% per year (totaling 12.5% over a 5 year cycle). In 2000, one household answered the long form questions on behalf of 5 other households, and in 2010 a single household provides data for between seven other households (5 year averages) and 39 other households (1 year averages for larger places). | V3: Surveys | W3: 2016 | AA3: Census Data is collected every 10 years by mail surveys to every household with primary data collection fields of population, gender, race and number of occupants. Overcounts are known to exist in student and dual-residence populations, while undercounts are a given for homeless and illegal immigrants. Errors arise from both sampling and non-sampling methods. Sampling errors are misrepresentations of a larger population based on the selection of the representative sample. Accuracy of the estimates depend in part on how typical the people within the sampled housing units are to others within their area. The Census estimates sampling error based on the population and its extent of variability. The long-form of the Census is distributed to a subset of households, and includes additional data related to households, economy, employment, occupation, as well as occupancy and building structure data. Household fields include: Total Households, Total Families, Households by Household Type by Household Size, Persons in Group Quarters by Detailed Group Quarters Type, Persons 25 Years and Over by Educational Attainment, Persons 16 Years and Over by Labor Force and Employment Status, Median Household Income, Median Family Income, Per Capita Income, Persons by Poverty Status in Previous Year. Occupancy fields include: Total Housing Units, Housing Units by Occupancy Status, Vacant Housing Units by Vacancy Status, Occupied Housing Units by Tenure, Median Housing Value, Median Contract Rent. | AI3: Census data is reliable as within the constraints of funding, staffing and legislation. Sampling and Non-sampling errors include, but are not limited to, missing survey responses, under and over counts, inverviewer error. | AJ3: NAD83/GCS_North_American_1983 | AK3: =IF(AO3="Static", "None", IF(AO3="Manual - monthly", "4th of month", IF(AO3="Automated - weekly", "Tuesday after 12AM", IF(AO3="Automated - monthly", "4th of month", IF(AO3="Manual - annual", "Annually", IF(AO3="Automated - broken", "Automation in progress", IF(AO3="Automated - daily", "Every day after midnight", ""))))))) -> None | AL3: =IF(AO3="Static", "None", IF(AO3="Manual - monthly", "Manual", IF(AO3="Automated - weekly", "Automated by Staging Server", IF(AO3="Automated - monthly", "Automated by Staging Server", IF(AO3="Manual - annual", "Manual", IF(AO3="Automated - broken", "Automated by Staging Server", IF(AO3="Automated - daily", "Automated by Staging Server", ""))))))) -> None | AO3: Static | AP3: 526 | AS3: Census zip codes demographics | AT3: 526 | AU3: 70+ | AW3: n/a | AX3: 43186 | AY3: =IF(DATEVALUE(AX3) < DATE(2014,7,1), 1, IF(DATEVALUE(AX3)<DATE(2015,7,1),2,IF(DATEVALUE(AX3)<DATE(2016,7,1),3,IF(DATEVALUE(AX3)<DATE(2017,7,1),4,IF(DATEVALUE(AX3)<DATE(2018,7,1),5,IF(DATEVALUE(AX3)<DATE(2019,7,1),6,IF(DATEVALUE(AX3) < DATE(2020,7,1), 7, IF(DATEVALUE(AX3) < DATE(2021,7,1), 8, IF(DATEVALUE(AX3) < DATE(2022,7,1), 9, IF(DATEVALUE(AX3) < DATE(2023,7,1), 10, IF(DATEVALUE(AX3) < DATE(2024,7,1), 11,IF(DATEVALUE(AX3) < DATE(2025,7,1),12,0)))))))))))) -> 5 | AZ3: =HYPERLINK("https://data.colorado.gov/dataset/Census-Block-Groups-in-Colorado-2016/gg8x-5kdz","gg8x-5kdz") -> gg8x-5kdz | BA3: =HYPERLINK("https://dev.socrata.com/foundry/data.colorado.gov/55mv-2ynf","55mv-2ynf") -> 55mv-2ynf | BB3: =HYPERLINK("https://data.colorado.gov/dataset/Census-Block-Groups-in-Colorado-2016/rwak-e74e","rwak-e74e") -> rwak-e74e | BC3: WGS84 | BD3: NOTE: To maintain source projection, select “Export Original” from export menu. To display on the web, export using any other option. | BF3: =IF(AND(MONTH(AX3)>=7,MONTH(AX3)<=9), 1, IF(AND(MONTH(AX3)>=9,MONTH(AX3)<=12), 2, IF(AND(MONTH(AX3)>=1,MONTH(AX3)<=3), 3, IF(AND(MONTH(AX3)>=4,MONTH(AX3)<=6), 4)))) -> 3 | BG3: =LEFT(XLOOKUP(AZ3, cimAllData!$B$2:B1002, cimAllData!$F$2:$F1002), 10) -> #REF! | BI3: Elizabeth Garner | BJ3: State Demographer | BK3: 303-864-7763 | BL3: Elizabeth.Garner@state.co.us
A4: Characterization of Lobbyist Clients in Colorado | B4: Information for each lobbyist, including contact details, and their associated client and contact details, client business description and the name of the CEO provided by the Colorado Department of State (CDOS). | C4: Lobbyist | D4: bic, gocodecolorado, colorado, sos, secretary of state, lobbyists, clients, contact, businesses, business descriptions | E4: Client | F4: Public Domain | G4: CDOS | H4: =IFERROR(G4&" - "&INDEX(Taxonomy!N:N,MATCH(G4,Taxonomy!M:M,0)),G4) -> CDOS | J4: CDOS | K4: =IFERROR(J4&" - "&INDEX(Taxonomy!N:N,MATCH(J4,Taxonomy!M:M,0)), J4) -> CDOS | L4: https://www.sos.state.co.us/ | M4: https://www.sos.state.co.us/pubs/lobby/FAQs/professional.html | N4: not public | O4: not public | Q4: Tabular | S4: State | X4: lobbyistlastname, lobbyistfirstname, lobbyistaddress0, lobbyistaddress1, lobbyistcity, lobbyiststate, lobbyistzip, primarylobbyistid, annuallobbyistregistrationid, clientname, clientlastname, clientfirstname, clientmiddlename, clientsuffix, clientaddress0, clientaddress1, clientcity, clientstate, clientzip, clientbusinessdescription, clienttypeofbusiness, ceolastname, ceofirstname, ceomiddlename | AA4: Information for each lobbyist, including contact details, and their associated client and contact details, client business description and the name of the CEO. Important to note that the key field is annualLobbyistRegistrationId, showing the lobbyist is registered for a given year, and is repeated as many times as there are unique clients to that lobbyist. A Lobbyist’s Registration Id updates with a new four digit prefix for every year the lobbyist is registered. The primaryLobbyistID field is the number is assigned when the lobbyist registers with the state, and the first four numbers are the year of original registration. The annual lobbyist registration identification number is updated when they register in a current fiscal year, and the first four numbers reflect status of the lobbyist when registering in a current fiscal year (for example, if they were registered in 2015, but did not update their registration in 2016, then the registration id would remain 2015 until they register in a new fiscal year). The data is updated as necessary to the main lobbyist online system via manual entry, however the updates to the Colorado Information Marketplace is only done weekly, every Monday night. | AK4: =IF(AO4="Static", "None", IF(AO4="Manual - monthly", "4th of month", IF(AO4="Automated - weekly", "Tuesday after 12AM", IF(AO4="Automated - monthly", "4th of month", IF(AO4="Manual - annual", "Annually", IF(AO4="Automated - broken", "Automation in progress", IF(AO4="Automated - daily", "Every day after midnight", ""))))))) -> None | AL4: =IF(AO4="Static", "None", IF(AO4="Manual - monthly", "Manual", IF(AO4="Automated - weekly", "Automated by Staging Server", IF(AO4="Automated - monthly", "Automated by Staging Server", IF(AO4="Manual - annual", "Manual", IF(AO4="Automated - broken", "Automated by Staging Server", IF(AO4="Automated - daily", "Automated by Staging Server", ""))))))) -> None | AO4: Static | AS4: Lobbyist and associated client name, contact, and client characterization | AT4: 14490 | AX4: 42547 | AY4: =IF(DATEVALUE(AX4) < DATE(2014,7,1), 1, IF(DATEVALUE(AX4)<DATE(2015,7,1),2,IF(DATEVALUE(AX4)<DATE(2016,7,1),3,IF(DATEVALUE(AX4)<DATE(2017,7,1),4,IF(DATEVALUE(AX4)<DATE(2018,7,1),5,IF(DATEVALUE(AX4)<DATE(2019,7,1),6,IF(DATEVALUE(AX4) < DATE(2020,7,1), 7, IF(DATEVALUE(AX4) < DATE(2021,7,1), 8, IF(DATEVALUE(AX4) < DATE(2022,7,1), 9, IF(DATEVALUE(AX4) < DATE(2023,7,1), 10, IF(DATEVALUE(AX4) < DATE(2024,7,1), 11,IF(DATEVALUE(AX4) < DATE(2025,7,1),12,0)))))))))))) -> 3 | AZ4: =HYPERLINK("https://data.colorado.gov/Legislative/Characterization-of-Lobbyist-Clients-in-Colorado/g89g-muvw","g89g-muvw") -> g89g-muvw | BA4: =HYPERLINK("https://data.colorado.gov/resource/kr2z-56yf.json","kr2z-56yf") -> kr2z-56yf | BE4: Joinable to: Bill Information and Position with Income of Lobbyist in Colorado, Directory of Lobbyist Clients in Colorado, Directory of Lobbyists in Colorado, Expenses for Lobbyists in Colorado, Subcontractors for Lobbyists in Colorado based on "primaryLobbyistId" | BF4: =IF(AND(MONTH(AX4)>=7,MONTH(AX4)<=9), 1, IF(AND(MONTH(AX4)>=9,MONTH(AX4)<=12), 2, IF(AND(MONTH(AX4)>=1,MONTH(AX4)<=3), 3, IF(AND(MONTH(AX4)>=4,MONTH(AX4)<=6), 4)))) -> 4 | BG4: =LEFT(XLOOKUP(AZ4, cimAllData!$B$2:B1003, cimAllData!$F$2:$F1003), 10) -> #REF! | BJ4: BIC Program Manager | BM4: Angela Lawson | BN4: Lobbyist Registration Program Manager | BO4: 303-894-2200, ext. 6304 | BP4: a.lawson@sos.state.co.us | BQ4: Sebbie Coleman | BR4: sebbie.coleman@sos.state.co.us
A5: Current Surface Water Conditions in Colorado | B5: Division of Water Resources (DWR) Current Surface Water Conditions. This is a list of all remote monitored stream, diversion, and reservoir gages within the state of Colorado. | C5: Water | D5: bic, streamflows, current conditions, gocode | E5: Water Resources | F5: Public Domain | G5: DWR | H5: =IFERROR(G5&" - "&INDEX(Taxonomy!N:N,MATCH(G5,Taxonomy!M:M,0)),G5) -> DWR | I5: http://water.state.co.us | J5: DWR | K5: =IFERROR(J5&" - "&INDEX(Taxonomy!N:N,MATCH(J5,Taxonomy!M:M,0)), J5) -> DWR | L5: http://water.state.co.us/Home/Pages/default.aspx | N5: not public | O5: not public | Q5: Tabular | S5: State | X5: DIV,WD,County,Station Name,Data Source,DWR Abbrev,USGS Station ID,Station Status,Station Type,Date Time,Variable,Stage,Amount,Units,Flag,More Information,Location,UTM x,UTM y,Location Accuracy, | Y5: 9/30/1999 | Z5: 7/18/2019 | AA5: Division of Water Resources (DWR) Current Surface Water Conditions. This is a list of all remote monitored stream, diversion, and reservoir gages within the state of Colorado. | AK5: =IF(AO5="Static", "None", IF(AO5="Manual - monthly", "4th of month", IF(AO5="Automated - weekly", "Tuesday after 12AM", IF(AO5="Automated - monthly", "4th of month", IF(AO5="Manual - annual", "Annually", IF(AO5="Automated - broken", "Automation in progress", IF(AO5="Automated - daily", "Every day after midnight", ""))))))) -> Every day after midnight | AL5: =IF(AO5="Static", "None", IF(AO5="Manual - monthly", "Manual", IF(AO5="Automated - weekly", "Automated by Staging Server", IF(AO5="Automated - monthly", "Automated by Staging Server", IF(AO5="Manual - annual", "Manual", IF(AO5="Automated - broken", "Automated by Staging Server", IF(AO5="Automated - daily", "Automated by Staging Server", ""))))))) -> Automated by Staging Server | AO5: Automated - daily | AX5: 41577 | AY5: =IF(DATEVALUE(AX5) < DATE(2014,7,1), 1, IF(DATEVALUE(AX5)<DATE(2015,7,1),2,IF(DATEVALUE(AX5)<DATE(2016,7,1),3,IF(DATEVALUE(AX5)<DATE(2017,7,1),4,IF(DATEVALUE(AX5)<DATE(2018,7,1),5,IF(DATEVALUE(AX5)<DATE(2019,7,1),6,IF(DATEVALUE(AX5) < DATE(2020,7,1), 7, IF(DATEVALUE(AX5) < DATE(2021,7,1), 8, IF(DATEVALUE(AX5) < DATE(2022,7,1), 9, IF(DATEVALUE(AX5) < DATE(2023,7,1), 10, IF(DATEVALUE(AX5) < DATE(2024,7,1), 11,IF(DATEVALUE(AX5) < DATE(2025,7,1),12,0)))))))))))) -> 1 | AZ5: 4yw9-a5y6 | BA5: 4yw9-a5y6 | BF5: =IF(AND(MONTH(AX5)>=7,MONTH(AX5)<=9), 1, IF(AND(MONTH(AX5)>=9,MONTH(AX5)<=12), 2, IF(AND(MONTH(AX5)>=1,MONTH(AX5)<=3), 3, IF(AND(MONTH(AX5)>=4,MONTH(AX5)<=6), 4)))) -> 2 | BG5: =LEFT(XLOOKUP(AZ5, cimAllData!$B$2:B1004, cimAllData!$F$2:$F1004), 10) -> #REF!
A6: Development Projects in Grand Junction Colorado 2019 | B6: 2019 Development Projects in Grand Junction, Colorado. | C6: Business | D6: bic, business, gocodecolorado, grand junction, grand, junction, city, mesa, county, western slope, development, parcels, projects, urban | E6: Business | F6: Creative Commons 1.0 Universal (Public Domain Dedication) | G6: City of Grand Junction | H6: =IFERROR(G6&" - "&INDEX(Taxonomy!N:N,MATCH(G6,Taxonomy!M:M,0)),G6) -> City of Grand Junction | I6: https://arcgis-app.gjcity.org/Business%20Map%20External/ | J6: CDOS | K6: =IFERROR(J6&" - "&INDEX(Taxonomy!N:N,MATCH(J6,Taxonomy!M:M,0)), J6) -> CDOS | L6: http://www.gjcity.org/Maps/ | M6: https://arcgis-app.gjcity.org/arcgis/rest/services/BusinessMap_external_MIL1/MapServer/54 | N6: Jackson Trappett | Q6: Vector Polygon | S6: City of Grand Junction | X6: objectid, casenumber, plannername, phone, casetype, applicationdate_1, description | AA6: Details for 2019 Development projects in Grand Junction, Colorado including case details, application, date, and a description of the project. | AC6: https://arcgis-app.gjcity.org/arcgis/rest/services/BusinessMap_external_MIL1/MapServer/55/metadata | AK6: =IF(AO6="Static", "None", IF(AO6="Manual - monthly", "4th of month", IF(AO6="Automated - weekly", "Tuesday after 12AM", IF(AO6="Automated - monthly", "4th of month", IF(AO6="Manual - annual", "Annually", IF(AO6="Automated - broken", "Automation in progress", IF(AO6="Automated - daily", "Every day after midnight", ""))))))) -> None | AL6: =iferror(IF(AO6="Static", "None", IF(AO6="Manual - monthly", "Manual", IF(AO6="Automated - weekly", "Automated by Staging Server", IF(AO6="Automated - monthly", "Automated by Staging Server", IF(AO6="Manual - annual", "Manual", IF(AO6="Automated - broken", "Automated by Staging Server", IF(AO6="Automated - daily", "Automated by Staging Server", ""))))))),"") -> None | AN6: Last updated 1/17/2020 | AO6: Static | AS6: Development project details for 2019 projects in Grand Junction Colorado. | AV6: 2222 kb | AX6: 43794 | AY6: =IF(DATEVALUE(AX6) < DATE(2014,7,1), 1, IF(DATEVALUE(AX6)<DATE(2015,7,1),2,IF(DATEVALUE(AX6)<DATE(2016,7,1),3,IF(DATEVALUE(AX6)<DATE(2017,7,1),4,IF(DATEVALUE(AX6)<DATE(2018,7,1),5,IF(DATEVALUE(AX6)<DATE(2019,7,1),6,IF(DATEVALUE(AX6) < DATE(2020,7,1), 7, IF(DATEVALUE(AX6) < DATE(2021,7,1), 8, IF(DATEVALUE(AX6) < DATE(2022,7,1), 9, IF(DATEVALUE(AX6) < DATE(2023,7,1), 10, IF(DATEVALUE(AX6) < DATE(2024,7,1), 11,IF(DATEVALUE(AX6) < DATE(2025,7,1),12,0)))))))))))) -> 7 | AZ6: 425c-yib4 | BA6: 425c-yib4 | BF6: =IF(AND(MONTH(AX6)>=7,MONTH(AX6)<=9), 1, IF(AND(MONTH(AX6)>=9,MONTH(AX6)<=12), 2, IF(AND(MONTH(AX6)>=1,MONTH(AX6)<=3), 3, IF(AND(MONTH(AX6)>=4,MONTH(AX6)<=6), 4)))) -> 2 | BG6: =LEFT(XLOOKUP(AZ6, cimAllData!$B$2:B1005, cimAllData!$F$2:$F1005), 10) -> #REF!
A7: Development Projects in Grand Junction Colorado 2020 | B7: 2020 Development Projects in Grand Junction, Colorado. | C7: Business | D7: bic, business, gocodecolorado, grand junction, grand, junction, city, mesa, county, western slope, development, parcels, projects, urban | E7: Business | F7: Creative Commons 1.0 Universal (Public Domain Dedication) | G7: City of Grand Junction | H7: =IFERROR(G7&" - "&INDEX(Taxonomy!N:N,MATCH(G7,Taxonomy!M:M,0)),G7) -> City of Grand Junction | I7: https://arcgis-app.gjcity.org/Business%20Map%20External/ | J7: CDOS | K7: =IFERROR(J7&" - "&INDEX(Taxonomy!N:N,MATCH(J7,Taxonomy!M:M,0)), J7) -> CDOS | L7: http://www.gjcity.org/Maps/ | M7: https://arcgis-app.gjcity.org/arcgis/rest/services/BusinessMap_external_MIL1/MapServer/54 | N7: Jackson Trappett | Q7: Vector Polygon | S7: City of Grand Junction | X7: objectid, casenumber, plannername, phone, casetype, applicationdate_1, description | AA7: Details for 2020 Development projects in Grand Junction, Colorado including case details, application, date, and a description of the project. | AC7: https://arcgis-app.gjcity.org/arcgis/rest/services/BusinessMap_external_MIL1/MapServer/55/metadata | AK7: =IF(AO7="Static", "None", IF(AO7="Manual - monthly", "4th of month", IF(AO7="Automated - weekly", "Tuesday after 12AM", IF(AO7="Automated - monthly", "4th of month", IF(AO7="Manual - annual", "Annually", IF(AO7="Automated - broken", "Automation in progress", IF(AO7="Automated - daily", "Every day after midnight", ""))))))) -> None | AL7: =iferror(IF(AO7="Static", "None", IF(AO7="Manual - monthly", "Manual", IF(AO7="Automated - weekly", "Automated by Staging Server", IF(AO7="Automated - monthly", "Automated by Staging Server", IF(AO7="Manual - annual", "Manual", IF(AO7="Automated - broken", "Automated by Staging Server", IF(AO7="Automated - daily", "Automated by Staging Server", ""))))))),"") -> None | AN7: Last updated 2/28/2024 | AO7: Static | AS7: Development project details for 2020 projects in Grand Junction Colorado. | AV7: 2222 kb | AX7: 45351 | AY7: =IF(DATEVALUE(AX7) < DATE(2014,7,1), 1, IF(DATEVALUE(AX7)<DATE(2015,7,1),2,IF(DATEVALUE(AX7)<DATE(2016,7,1),3,IF(DATEVALUE(AX7)<DATE(2017,7,1),4,IF(DATEVALUE(AX7)<DATE(2018,7,1),5,IF(DATEVALUE(AX7)<DATE(2019,7,1),6,IF(DATEVALUE(AX7) < DATE(2020,7,1), 7, IF(DATEVALUE(AX7) < DATE(2021,7,1), 8, IF(DATEVALUE(AX7) < DATE(2022,7,1), 9, IF(DATEVALUE(AX7) < DATE(2023,7,1), 10, IF(DATEVALUE(AX7) < DATE(2024,7,1), 11,IF(DATEVALUE(AX7) < DATE(2025,7,1),12,0)))))))))))) -> 11 | AZ7: u98h-pi4e | BA7: u98h-pi4e | BF7: =IF(AND(MONTH(AX7)>=7,MONTH(AX7)<=9), 1, IF(AND(MONTH(AX7)>=9,MONTH(AX7)<=12), 2, IF(AND(MONTH(AX7)>=1,MONTH(AX7)<=3), 3, IF(AND(MONTH(AX7)>=4,MONTH(AX7)<=6), 4)))) -> 3 | BG7: =LEFT(XLOOKUP(AZ7, cimAllData!$B$2:B1006, cimAllData!$F$2:$F1006), 10) -> #REF!
A8: Development Projects in Grand Junction Colorado 2021 | B8: 2021 Development Projects in Grand Junction, Colorado. | C8: Business | D8: bic, business, gocodecolorado, grand junction, grand, junction, city, mesa, county, western slope, development, parcels, projects, urban | E8: Business | F8: Creative Commons 1.0 Universal (Public Domain Dedication) | G8: City of Grand Junction | H8: =IFERROR(G8&" - "&INDEX(Taxonomy!N:N,MATCH(G8,Taxonomy!M:M,0)),G8) -> City of Grand Junction | I8: https://arcgis-app.gjcity.org/Business%20Map%20External/ | J8: CDOS | K8: =IFERROR(J8&" - "&INDEX(Taxonomy!N:N,MATCH(J8,Taxonomy!M:M,0)), J8) -> CDOS | L8: http://www.gjcity.org/Maps/ | M8: https://arcgis-app.gjcity.org/arcgis/rest/services/BusinessMap_external_MIL1/MapServer/54 | N8: Jackson Trappett | Q8: Vector Polygon | S8: City of Grand Junction | X8: objectid, casenumber, plannername, phone, casetype, applicationdate_1, description | AA8: Details for 2021 Development projects in Grand Junction, Colorado including case details, application, date, and a description of the project. | AC8: https://arcgis-app.gjcity.org/arcgis/rest/services/BusinessMap_external_MIL1/MapServer/55/metadata | AK8: =IF(AO8="Static", "None", IF(AO8="Manual - monthly", "4th of month", IF(AO8="Automated - weekly", "Tuesday after 12AM", IF(AO8="Automated - monthly", "4th of month", IF(AO8="Manual - annual", "Annually", IF(AO8="Automated - broken", "Automation in progress", IF(AO8="Automated - daily", "Every day after midnight", ""))))))) -> None | AL8: =iferror(IF(AO8="Static", "None", IF(AO8="Manual - monthly", "Manual", IF(AO8="Automated - weekly", "Automated by Staging Server", IF(AO8="Automated - monthly", "Automated by Staging Server", IF(AO8="Manual - annual", "Manual", IF(AO8="Automated - broken", "Automated by Staging Server", IF(AO8="Automated - daily", "Automated by Staging Server", ""))))))),"") -> None | AN8: Last updated 2/28/2024 | AO8: Static | AS8: Development project details for 2021 projects in Grand Junction Colorado. | AV8: 2222 kb | AX8: 45351 | AY8: =IF(DATEVALUE(AX8) < DATE(2014,7,1), 1, IF(DATEVALUE(AX8)<DATE(2015,7,1),2,IF(DATEVALUE(AX8)<DATE(2016,7,1),3,IF(DATEVALUE(AX8)<DATE(2017,7,1),4,IF(DATEVALUE(AX8)<DATE(2018,7,1),5,IF(DATEVALUE(AX8)<DATE(2019,7,1),6,IF(DATEVALUE(AX8) < DATE(2020,7,1), 7, IF(DATEVALUE(AX8) < DATE(2021,7,1), 8, IF(DATEVALUE(AX8) < DATE(2022,7,1), 9, IF(DATEVALUE(AX8) < DATE(2023,7,1), 10, IF(DATEVALUE(AX8) < DATE(2024,7,1), 11,IF(DATEVALUE(AX8) < DATE(2025,7,1),12,0)))))))))))) -> 11 | AZ8: dcpy-bvxg | BA8: dcpy-bvxg | BF8: =IF(AND(MONTH(AX8)>=7,MONTH(AX8)<=9), 1, IF(AND(MONTH(AX8)>=9,MONTH(AX8)<=12), 2, IF(AND(MONTH(AX8)>=1,MONTH(AX8)<=3), 3, IF(AND(MONTH(AX8)>=4,MONTH(AX8)<=6), 4)))) -> 3 | BG8: =LEFT(XLOOKUP(AZ8, cimAllData!$B$2:B1007, cimAllData!$F$2:$F1007), 10) -> #REF!
A9: Development Projects in Grand Junction Colorado 2022 | B9: 2022 Development Projects in Grand Junction, Colorado. | C9: Business | D9: bic, business, gocodecolorado, grand junction, grand, junction, city, mesa, county, western slope, development, parcels, projects, urban | E9: Business | F9: Creative Commons 1.0 Universal (Public Domain Dedication) | G9: City of Grand Junction | H9: =IFERROR(G9&" - "&INDEX(Taxonomy!N:N,MATCH(G9,Taxonomy!M:M,0)),G9) -> City of Grand Junction | I9: https://arcgis-app.gjcity.org/Business%20Map%20External/ | J9: CDOS | K9: =IFERROR(J9&" - "&INDEX(Taxonomy!N:N,MATCH(J9,Taxonomy!M:M,0)), J9) -> CDOS | L9: http://www.gjcity.org/Maps/ | M9: https://arcgis-app.gjcity.org/arcgis/rest/services/BusinessMap_external_MIL1/MapServer/54 | N9: Jackson Trappett | Q9: Vector Polygon | S9: City of Grand Junction | X9: objectid, casenumber, plannername, phone, casetype, applicationdate_1, description | AA9: Details for 2022 Development projects in Grand Junction, Colorado including case details, application, date, and a description of the project. | AC9: https://arcgis-app.gjcity.org/arcgis/rest/services/BusinessMap_external_MIL1/MapServer/55/metadata | AK9: =IF(AO9="Static", "None", IF(AO9="Manual - monthly", "4th of month", IF(AO9="Automated - weekly", "Tuesday after 12AM", IF(AO9="Automated - monthly", "4th of month", IF(AO9="Manual - annual", "Annually", IF(AO9="Automated - broken", "Automation in progress", IF(AO9="Automated - daily", "Every day after midnight", ""))))))) -> None | AL9: =iferror(IF(AO9="Static", "None", IF(AO9="Manual - monthly", "Manual", IF(AO9="Automated - weekly", "Automated by Staging Server", IF(AO9="Automated - monthly", "Automated by Staging Server", IF(AO9="Manual - annual", "Manual", IF(AO9="Automated - broken", "Automated by Staging Server", IF(AO9="Automated - daily", "Automated by Staging Server", ""))))))),"") -> None | AN9: Last updated 2/28/2024 | AO9: Static | AS9: Development project details for 2022 projects in Grand Junction Colorado. | AV9: 2222 kb | AX9: 45351 | AY9: =IF(DATEVALUE(AX9) < DATE(2014,7,1), 1, IF(DATEVALUE(AX9)<DATE(2015,7,1),2,IF(DATEVALUE(AX9)<DATE(2016,7,1),3,IF(DATEVALUE(AX9)<DATE(2017,7,1),4,IF(DATEVALUE(AX9)<DATE(2018,7,1),5,IF(DATEVALUE(AX9)<DATE(2019,7,1),6,IF(DATEVALUE(AX9) < DATE(2020,7,1), 7, IF(DATEVALUE(AX9) < DATE(2021,7,1), 8, IF(DATEVALUE(AX9) < DATE(2022,7,1), 9, IF(DATEVALUE(AX9) < DATE(2023,7,1), 10, IF(DATEVALUE(AX9) < DATE(2024,7,1), 11,IF(DATEVALUE(AX9) < DATE(2025,7,1),12,0)))))))))))) -> 11 | AZ9: vzyy-dwzb | BA9: vzyy-dwzb | BF9: =IF(AND(MONTH(AX9)>=7,MONTH(AX9)<=9), 1, IF(AND(MONTH(AX9)>=9,MONTH(AX9)<=12), 2, IF(AND(MONTH(AX9)>=1,MONTH(AX9)<=3), 3, IF(AND(MONTH(AX9)>=4,MONTH(AX9)<=6), 4)))) -> 3 | BG9: =LEFT(XLOOKUP(AZ9, cimAllData!$B$2:B1008, cimAllData!$F$2:$F1008), 10) -> #REF!
A10: Development Projects in Grand Junction Colorado 2023 | B10: 2023 Development Projects in Grand Junction, Colorado. | C10: Business | D10: bic, business, gocodecolorado, grand junction, grand, junction, city, mesa, county, western slope, development, parcels, projects, urban | E10: Business | F10: Creative Commons 1.0 Universal (Public Domain Dedication) | G10: City of Grand Junction | H10: =IFERROR(G10&" - "&INDEX(Taxonomy!N:N,MATCH(G10,Taxonomy!M:M,0)),G10) -> City of Grand Junction | I10: https://arcgis-app.gjcity.org/Business%20Map%20External/ | J10: CDOS | K10: =IFERROR(J10&" - "&INDEX(Taxonomy!N:N,MATCH(J10,Taxonomy!M:M,0)), J10) -> CDOS | L10: http://www.gjcity.org/Maps/ | M10: https://arcgis-app.gjcity.org/arcgis/rest/services/BusinessMap_external_MIL1/MapServer/54 | N10: Jackson Trappett | Q10: Vector Polygon | S10: City of Grand Junction | X10: objectid, casenumber, plannername, phone, casetype, applicationdate_1, description | AA10: Details for 2023 Development projects in Grand Junction, Colorado including case details, application, date, and a description of the project. | AC10: https://arcgis-app.gjcity.org/arcgis/rest/services/BusinessMap_external_MIL1/MapServer/55/metadata | AK10: =IF(AO10="Static", "None", IF(AO10="Manual - monthly", "4th of month", IF(AO10="Automated - weekly", "Tuesday after 12AM", IF(AO10="Automated - monthly", "4th of month", IF(AO10="Manual - annual", "Annually", IF(AO10="Automated - broken", "Automation in progress", IF(AO10="Automated - daily", "Every day after midnight", ""))))))) -> None | AL10: =iferror(IF(AO10="Static", "None", IF(AO10="Manual - monthly", "Manual", IF(AO10="Automated - weekly", "Automated by Staging Server", IF(AO10="Automated - monthly", "Automated by Staging Server", IF(AO10="Manual - annual", "Manual", IF(AO10="Automated - broken", "Automated by Staging Server", IF(AO10="Automated - daily", "Automated by Staging Server", ""))))))),"") -> None | AN10: Last updated 2/28/2024 | AO10: Static | AS10: Development project details for 2023 projects in Grand Junction Colorado. | AV10: 2222 kb | AX10: 45351 | AY10: =IF(DATEVALUE(AX10) < DATE(2014,7,1), 1, IF(DATEVALUE(AX10)<DATE(2015,7,1),2,IF(DATEVALUE(AX10)<DATE(2016,7,1),3,IF(DATEVALUE(AX10)<DATE(2017,7,1),4,IF(DATEVALUE(AX10)<DATE(2018,7,1),5,IF(DATEVALUE(AX10)<DATE(2019,7,1),6,IF(DATEVALUE(AX10) < DATE(2020,7,1), 7, IF(DATEVALUE(AX10) < DATE(2021,7,1), 8, IF(DATEVALUE(AX10) < DATE(2022,7,1), 9, IF(DATEVALUE(AX10) < DATE(2023,7,1), 10, IF(DATEVALUE(AX10) < DATE(2024,7,1), 11,IF(DATEVALUE(AX10) < DATE(2025,7,1),12,0)))))))))))) -> 11 | AZ10: h5jd-ew98 | BA10: h5jd-ew98 | BF10: =IF(AND(MONTH(AX10)>=7,MONTH(AX10)<=9), 1, IF(AND(MONTH(AX10)>=9,MONTH(AX10)<=12), 2, IF(AND(MONTH(AX10)>=1,MONTH(AX10)<=3), 3, IF(AND(MONTH(AX10)>=4,MONTH(AX10)<=6), 4)))) -> 3 | BG10: =LEFT(XLOOKUP(AZ10, cimAllData!$B$2:B1009, cimAllData!$F$2:$F1009), 10) -> #REF!
A11: Development Projects in Grand Junction Colorado 2024 | B11: 2024 Development Projects in Grand Junction, Colorado. | C11: Business | D11: bic, business, gocodecolorado, grand junction, grand, junction, city, mesa, county, western slope, development, parcels, projects, urban | E11: Business | F11: Creative Commons 1.0 Universal (Public Domain Dedication) | G11: City of Grand Junction | H11: =IFERROR(G11&" - "&INDEX(Taxonomy!N:N,MATCH(G11,Taxonomy!M:M,0)),G11) -> City of Grand Junction | I11: https://arcgis-app.gjcity.org/Business%20Map%20External/ | J11: CDOS | K11: =IFERROR(J11&" - "&INDEX(Taxonomy!N:N,MATCH(J11,Taxonomy!M:M,0)), J11) -> CDOS | L11: http://www.gjcity.org/Maps/ | M11: https://arcgis-app.gjcity.org/arcgis/rest/services/BusinessMap_external_MIL1/MapServer/54 | N11: Jackson Trappett | Q11: Vector Polygon | S11: City of Grand Junction | X11: objectid, casenumber, plannername, phone, casetype, applicationdate_1, description | AA11: Details for 2024 Development projects in Grand Junction, Colorado including case details, application, date, and a description of the project. | AC11: https://arcgis-app.gjcity.org/arcgis/rest/services/BusinessMap_external_MIL1/MapServer/55/metadata | AK11: =IF(AO11="Static", "None", IF(AO11="Manual - monthly", "4th of month", IF(AO11="Automated - weekly", "Tuesday after 12AM", IF(AO11="Automated - monthly", "4th of month", IF(AO11="Manual - annual", "Annually", IF(AO11="Automated - broken", "Automation in progress", IF(AO11="Automated - daily", "Every day after midnight", ""))))))) -> Annually | AL11: =iferror(IF(AO11="Static", "None", IF(AO11="Manual - monthly", "Manual", IF(AO11="Automated - weekly", "Automated by Staging Server", IF(AO11="Automated - monthly", "Automated by Staging Server", IF(AO11="Manual - annual", "Manual", IF(AO11="Automated - broken", "Automated by Staging Server", IF(AO11="Automated - daily", "Automated by Staging Server", ""))))))),"") -> Manual | AN11: Last updated 2/28/2024 | AO11: Manual - annual | AS11: Development project details for 2024 projects in Grand Junction Colorado. | AV11: 2222 kb | AX11: 45351 | AY11: =IF(DATEVALUE(AX11) < DATE(2014,7,1), 1, IF(DATEVALUE(AX11)<DATE(2015,7,1),2,IF(DATEVALUE(AX11)<DATE(2016,7,1),3,IF(DATEVALUE(AX11)<DATE(2017,7,1),4,IF(DATEVALUE(AX11)<DATE(2018,7,1),5,IF(DATEVALUE(AX11)<DATE(2019,7,1),6,IF(DATEVALUE(AX11) < DATE(2020,7,1), 7, IF(DATEVALUE(AX11) < DATE(2021,7,1), 8, IF(DATEVALUE(AX11) < DATE(2022,7,1), 9, IF(DATEVALUE(AX11) < DATE(2023,7,1), 10, IF(DATEVALUE(AX11) < DATE(2024,7,1), 11,IF(DATEVALUE(AX11) < DATE(2025,7,1),12,0)))))))))))) -> 11 | AZ11: i35i-dd8x | BA11: i35i-dd8x | BF11: =IF(AND(MONTH(AX11)>=7,MONTH(AX11)<=9), 1, IF(AND(MONTH(AX11)>=9,MONTH(AX11)<=12), 2, IF(AND(MONTH(AX11)>=1,MONTH(AX11)<=3), 3, IF(AND(MONTH(AX11)>=4,MONTH(AX11)<=6), 4)))) -> 3 | BG11: =LEFT(XLOOKUP(AZ11, cimAllData!$B$2:B1010, cimAllData!$F$2:$F1010), 10) -> #REF!
A12: Directory of Lobbyist Clients in Colorado | B12: Lobbyist name and address and the names and addresses of their associated clients provided by the Colorado Department of State (CDOS). | C12: Lobbyist | D12: bic, gocodecolorado, colorado, sos, secretary of state, lobbyists, expenses, contact, directory, clients | E12: Client | F12: Public Domain | G12: CDOS | H12: =IFERROR(G12&" - "&INDEX(Taxonomy!N:N,MATCH(G12,Taxonomy!M:M,0)),G12) -> CDOS | J12: CDOS | K12: =IFERROR(J12&" - "&INDEX(Taxonomy!N:N,MATCH(J12,Taxonomy!M:M,0)), J12) -> CDOS | L12: https://www.sos.state.co.us/ | M12: https://www.sos.state.co.us/pubs/lobby/FAQs/professional.html | N12: not public | O12: not public | Q12: Tabular | S12: State | X12: lobbyistlastname, lobbyistfirstname, lobbyistaddress0, lobbyistaddress1, lobbyistcity, lobbyiststate, lobbyistzip, primarylobbyistid, annuallobbyistregistrationid, clientname, clientaddress0, clientaddress1, clientcity, clientstate, clientzip | AA12: All of the lobbyists and all of the clients for Colorado, except for state lobbyists, also known as official State Liaisons, who are responsible for lobbying on behalf of a state agency and therefore have no "client". The primaryLobbyistID field is the number assigned when the lobbyist registers with the state, and the first four numbers are the year of original registration. The annual lobbyist registration identification number is updated when they register in a current fiscal year, and the first four numbers reflect status of the lobbyist when registering in a current fiscal year (for example, if they were registered in 2015, but did not update their registration in 2016, then the registration id would remain 2015 until they register in a new fiscal year). The data is updated as necessary to the main lobbyist online system via manual entry, however the updates to the Colorado Information Marketplace is only done weekly, every Monday night. | AC12: http://www.sos.state.co.us/pubs/lobby/FAQ.html | AK12: =IF(AO12="Static", "None", IF(AO12="Manual - monthly", "4th of month", IF(AO12="Automated - weekly", "Tuesday after 12AM", IF(AO12="Automated - monthly", "4th of month", IF(AO12="Manual - annual", "Annually", IF(AO12="Automated - broken", "Automation in progress", IF(AO12="Automated - daily", "Every day after midnight", ""))))))) -> None | AL12: =IF(AO12="Static", "None", IF(AO12="Manual - monthly", "Manual", IF(AO12="Automated - weekly", "Automated by Staging Server", IF(AO12="Automated - monthly", "Automated by Staging Server", IF(AO12="Manual - annual", "Manual", IF(AO12="Automated - broken", "Automated by Staging Server", IF(AO12="Automated - daily", "Automated by Staging Server", ""))))))) -> None | AO12: Static | AS12: Lobbyist and associated client name and contact | AT12: 57962 | AX12: 42547 | AY12: =IF(DATEVALUE(AX12) < DATE(2014,7,1), 1, IF(DATEVALUE(AX12)<DATE(2015,7,1),2,IF(DATEVALUE(AX12)<DATE(2016,7,1),3,IF(DATEVALUE(AX12)<DATE(2017,7,1),4,IF(DATEVALUE(AX12)<DATE(2018,7,1),5,IF(DATEVALUE(AX12)<DATE(2019,7,1),6,IF(DATEVALUE(AX12) < DATE(2020,7,1), 7, IF(DATEVALUE(AX12) < DATE(2021,7,1), 8, IF(DATEVALUE(AX12) < DATE(2022,7,1), 9, IF(DATEVALUE(AX12) < DATE(2023,7,1), 10, IF(DATEVALUE(AX12) < DATE(2024,7,1), 11,IF(DATEVALUE(AX12) < DATE(2025,7,1),12,0)))))))))))) -> 3 | AZ12: =HYPERLINK("https://data.colorado.gov/Legislative/Directory-of-Lobbyist-Clients-in-Colorado/35k5-cv8s","35k5-cv8s") -> 35k5-cv8s | BA12: =HYPERLINK("https://data.colorado.gov/resource/dm35-83um.json","dm35-83um") -> dm35-83um | BE12: Joinable to: Bill Information and Position with Income of Lobbyist in Colorado, Characterization of Lobbyist Clients in Colorado, Directory of Lobbyists in Colorado, Expenses for Lobbyists in Colorado, Subcontractors for Lobbyists in Colorado based on "primaryLobbyistId" | BF12: =IF(AND(MONTH(AX12)>=7,MONTH(AX12)<=9), 1, IF(AND(MONTH(AX12)>=9,MONTH(AX12)<=12), 2, IF(AND(MONTH(AX12)>=1,MONTH(AX12)<=3), 3, IF(AND(MONTH(AX12)>=4,MONTH(AX12)<=6), 4)))) -> 4 | BG12: =LEFT(XLOOKUP(AZ12, cimAllData!$B$2:B1011, cimAllData!$F$2:$F1011), 10) -> #REF! | BJ12: BIC Program Manager | BM12: Angela Lawson | BN12: Lobbyist Registration Program Manager | BO12: 303-894-2200, ext. 6304 | BP12: a.lawson@sos.state.co.us | BQ12: Sebbie Coleman | BR12: sebbie.coleman@sos.state.co.us
A13: Directory of Lobbyists in Colorado | B13: Information for each registered lobbyist, including contact details, and their associated income and expenses as summarized by month and associated report date for the State of Colorado dating back to 1995 provided by the Colorado Department of State (CDOS). | C13: Lobbyist | D13: bic, gocodecolorado, colorado, sos, secretary of state, lobbyists, expenses, contact, directory, income summary, income | E13: Lobbyist | F13: Public Domain | G13: CDOS | H13: =IFERROR(G13&" - "&INDEX(Taxonomy!N:N,MATCH(G13,Taxonomy!M:M,0)),G13) -> CDOS | J13: CDOS | K13: =IFERROR(J13&" - "&INDEX(Taxonomy!N:N,MATCH(J13,Taxonomy!M:M,0)), J13) -> CDOS | L13: https://www.sos.state.co.us/ | M13: https://www.sos.state.co.us/pubs/lobby/FAQs/professional.html | N13: not public | O13: not public | Q13: Tabular | S13: State | X13: lobbyistlastname, lobbyistfirstname, lobbyistaddress0, lobbyistaddress1, lobbyistcity, lobbyiststate, lobbyistzip, officialstatelobbyist, primarylobbyistid, annuallobbyistregistrationid, datedisclosurefiled, datedisclosurelastmodified, businessassociatedwithpendinglegislation, totalmonthlyincome, totalmonthlyexpenses, reportmonth, fiscalyear, reportduedate | Y13: 08/15/1994 | Z13: 07/20/2017 | AA13: Expenses and income summarized by month associated with lobbying activities. In a reporting month, income is reported based on the date that it is actually received. For example, in the event that a payment is made cumulatively over a three month period, they must report the full three month payment when the payment was received. If a lobbyist has multiple payments received by various clients, each dollar amount is reported separately by each client. If a lobbyist receives multiple payments on multiple bills from a single client, the monthly income report will be the total of what the client is paying the lobbyist for all of lobbying activities on the multiple bills. The statute specifies that lobbyists report the total amount they receive from the client, so in some cases the monthly dollar amount reported by a lobbyist is the total amount received may reflect a payment paid for a number of bills and activities. The payments are not itemized by bills or activities. In this dataset income is summarized by month. | AK13: =IF(AO13="Static", "None", IF(AO13="Manual - monthly", "4th of month", IF(AO13="Automated - weekly", "Tuesday after 12AM", IF(AO13="Automated - monthly", "4th of month", IF(AO13="Manual - annual", "Annually", IF(AO13="Automated - broken", "Automation in progress", IF(AO13="Automated - daily", "Every day after midnight", ""))))))) -> None | AL13: =IF(AO13="Static", "None", IF(AO13="Manual - monthly", "Manual", IF(AO13="Automated - weekly", "Automated by Staging Server", IF(AO13="Automated - monthly", "Automated by Staging Server", IF(AO13="Manual - annual", "Manual", IF(AO13="Automated - broken", "Automated by Staging Server", IF(AO13="Automated - daily", "Automated by Staging Server", ""))))))) -> None | AO13: Static | AS13: Lobbyist name, id, address, and income and expense by month | AT13: 141460 | AX13: 42547 | AY13: =IF(DATEVALUE(AX13) < DATE(2014,7,1), 1, IF(DATEVALUE(AX13)<DATE(2015,7,1),2,IF(DATEVALUE(AX13)<DATE(2016,7,1),3,IF(DATEVALUE(AX13)<DATE(2017,7,1),4,IF(DATEVALUE(AX13)<DATE(2018,7,1),5,IF(DATEVALUE(AX13)<DATE(2019,7,1),6,IF(DATEVALUE(AX13) < DATE(2020,7,1), 7, IF(DATEVALUE(AX13) < DATE(2021,7,1), 8, IF(DATEVALUE(AX13) < DATE(2022,7,1), 9, IF(DATEVALUE(AX13) < DATE(2023,7,1), 10, IF(DATEVALUE(AX13) < DATE(2024,7,1), 11,IF(DATEVALUE(AX13) < DATE(2025,7,1),12,0)))))))))))) -> 3 | AZ13: =HYPERLINK("https://data.colorado.gov/Legislative/Directory-of-Lobbyists-in-Colorado/bqa5-gr84","bqa5-gr84") -> bqa5-gr84 | BA13: =HYPERLINK("https://data.colorado.gov/resource/4xaw-3ja7.json","4xaw-3ja7") -> 4xaw-3ja7 | BE13: Joinable to: Bill Information and Position with Income of Lobbyist in Colorado, Characterization of Lobbyist Clients in Colorado, Directory of Lobbyist Clients in Colorado, Expenses for Lobbyists in Colorado, Subcontractors for Lobbyists in Colorado based on "primaryLobbyistId" | BF13: =IF(AND(MONTH(AX13)>=7,MONTH(AX13)<=9), 1, IF(AND(MONTH(AX13)>=9,MONTH(AX13)<=12), 2, IF(AND(MONTH(AX13)>=1,MONTH(AX13)<=3), 3, IF(AND(MONTH(AX13)>=4,MONTH(AX13)<=6), 4)))) -> 4 | BG13: =LEFT(XLOOKUP(AZ13, cimAllData!$B$2:B1012, cimAllData!$F$2:$F1012), 10) -> #REF! | BJ13: BIC Program Manager | BM13: Angela Lawson | BN13: Lobbyist Registration Program Manager | BO13: 303-894-2200, ext. 6304 | BP13: a.lawson@sos.state.co.us | BQ13: Sebbie Coleman | BR13: sebbie.coleman@sos.state.co.us
A14: Expenses for Lobbyists in Colorado | B14: Registered lobbyist expenses for the State of Colorado dating back to 1995 provided by the Colorado Department of State (CDOS). | C14: Lobbyist | D14: bic, gocodecolorado, colorado, sos, secretary of state, lobbyists, expenses, media buys, gifts and entertainment, reimbursements, reimbursable expenses | E14: Bills | F14: Public Domain | G14: CDOS | H14: =IFERROR(G14&" - "&INDEX(Taxonomy!N:N,MATCH(G14,Taxonomy!M:M,0)),G14) -> CDOS | J14: CDOS | K14: =IFERROR(J14&" - "&INDEX(Taxonomy!N:N,MATCH(J14,Taxonomy!M:M,0)), J14) -> CDOS | L14: https://www.sos.state.co.us/ | M14: https://www.sos.state.co.us/pubs/lobby/FAQs/professional.html | N14: not public | O14: not public | Q14: Tabular | S14: State | X14: lobbyistlastname, lobbyistfirstname, lobbyistaddress0, lobbyistaddress1, lobbyistcity, lobbyiststate, lobbyistzip, primarylobbyistid, annuallobbyistregistrationid, officialstatelobbyist, expenditurename, expenditureamount, expenditurereceiptdate, expenditurepurpose, expenditureformediaflag, reportmonth, fiscalyear, reportduedate | Y14: 01/01/1995 | Z14: 09/30/2017 | AA14: Expenses of the lobbyist, and the purpose of the expense. Expenses are broken into three categories: Media, Gifts and Entertainment, and Other (for example, travel, parking, cell phone, etc.) This file includes expenses for all of the lobbyists, including state lobbyists, also known as official State Liaisons, who are responsible for lobbying on behalf of a state agency. State Liaisons do not itemize their expenses, they only report public funds. The primaryLobbyistID field is the number is assigned when the lobbyist registers with the state, and the first four numbers are the year of original registration. The annual lobbyist registration identification number is updated when they register in a current fiscal year, and the first four numbers reflect status of the lobbyist when registering in a current fiscal year (for example, if they were registered in 2015, but did not update their registration in 2016, then the registration id would remain 2015 until they register in a new fiscal year). The data is updated as necessary to the main lobbyist online system via manual entry, however the updates to the Colorado Information Marketplace is only done weekly, every Monday night. Data goes back to 1995, but in 2002 a mandate established that the secretary of state transition to an online system. Then in 2010 Senate Bill 10-87, among other major changes, shifted the lobbyist registration and disclosure periods to the state fiscal year rather than the calendar year. | AK14: =IF(AO14="Static", "None", IF(AO14="Manual - monthly", "4th of month", IF(AO14="Automated - weekly", "Tuesday after 12AM", IF(AO14="Automated - monthly", "4th of month", IF(AO14="Manual - annual", "Annually", IF(AO14="Automated - broken", "Automation in progress", IF(AO14="Automated - daily", "Every day after midnight", ""))))))) -> None | AL14: =IF(AO14="Static", "None", IF(AO14="Manual - monthly", "Manual", IF(AO14="Automated - weekly", "Automated by Staging Server", IF(AO14="Automated - monthly", "Automated by Staging Server", IF(AO14="Manual - annual", "Manual", IF(AO14="Automated - broken", "Automated by Staging Server", IF(AO14="Automated - daily", "Automated by Staging Server", ""))))))) -> None | AO14: Static | AS14: Lobbyist name, id, address, and name, amount, and date of expenditures | AT14: 66266 | AX14: 42547 | AY14: =IF(DATEVALUE(AX14) < DATE(2014,7,1), 1, IF(DATEVALUE(AX14)<DATE(2015,7,1),2,IF(DATEVALUE(AX14)<DATE(2016,7,1),3,IF(DATEVALUE(AX14)<DATE(2017,7,1),4,IF(DATEVALUE(AX14)<DATE(2018,7,1),5,IF(DATEVALUE(AX14)<DATE(2019,7,1),6,IF(DATEVALUE(AX14) < DATE(2020,7,1), 7, IF(DATEVALUE(AX14) < DATE(2021,7,1), 8, IF(DATEVALUE(AX14) < DATE(2022,7,1), 9, IF(DATEVALUE(AX14) < DATE(2023,7,1), 10, IF(DATEVALUE(AX14) < DATE(2024,7,1), 11,IF(DATEVALUE(AX14) < DATE(2025,7,1),12,0)))))))))))) -> 3 | AZ14: =HYPERLINK("https://data.colorado.gov/Legislative/Expenses-for-Lobbyists-in-Colorado/eqsm-7ah7","eqsm-7ah7") -> eqsm-7ah7 | BA14: =HYPERLINK("https://data.colorado.gov/resource/wkgc-9sne.json","wkgc-9sne") -> wkgc-9sne | BE14: Joinable to: Bill Information and Position with Income of Lobbyist in Colorado, Characterization of Lobbyist Clients in Colorado, Directory of Lobbyist Clients in Colorado, Directory of Lobbyists in Colorado, Subcontractors for Lobbyists in Colorado based on "primaryLobbyistId" | BF14: =IF(AND(MONTH(AX14)>=7,MONTH(AX14)<=9), 1, IF(AND(MONTH(AX14)>=9,MONTH(AX14)<=12), 2, IF(AND(MONTH(AX14)>=1,MONTH(AX14)<=3), 3, IF(AND(MONTH(AX14)>=4,MONTH(AX14)<=6), 4)))) -> 4 | BG14: =LEFT(XLOOKUP(AZ14, cimAllData!$B$2:B1013, cimAllData!$F$2:$F1013), 10) -> #REF! | BJ14: BIC Program Manager | BM14: Angela Lawson | BN14: Lobbyist Registration Program Manager | BO14: 303-894-2200, ext. 6304 | BP14: a.lawson@sos.state.co.us | BQ14: Sebbie Coleman | BR14: sebbie.coleman@sos.state.co.us
A15: Farmers Markets in Colorado 2017 | B15: Farmers’ Markets name, location, and dates of operation for 2014 in Colorado provided and maintained by the Colorado Department of Agriculture. | C15: Agriculture | D15: bic, gocodecolorado, farmer, farmers, markets, grocery, food, ag, agriculture, colorado, fresh, local, locavore | E15: Markets | F15: Public Domain | G15: CDA | H15: =IFERROR(G15&" - "&INDEX(Taxonomy!N:N,MATCH(G15,Taxonomy!M:M,0)),G15) -> CDA | J15: CDA | K15: =IFERROR(J15&" - "&INDEX(Taxonomy!N:N,MATCH(J15,Taxonomy!M:M,0)), J15) -> CDA | L15: https://www.colorado.gov/agmain | AA15: Farmers’ Markets name, location, and dates of operation for 2014 in Colorado provided and maintained by the Colorado Department of Agriculture. | AK15: =IF(AO15="Static", "None", IF(AO15="Manual - monthly", "4th of month", IF(AO15="Automated - weekly", "Tuesday after 12AM", IF(AO15="Automated - monthly", "4th of month", IF(AO15="Manual - annual", "Annually", IF(AO15="Automated - broken", "Automation in progress", IF(AO15="Automated - daily", "Every day after midnight", ""))))))) -> None | AL15: =IF(AO15="Static", "None", IF(AO15="Manual - monthly", "Manual", IF(AO15="Automated - weekly", "Automated by Staging Server", IF(AO15="Automated - monthly", "Automated by Staging Server", IF(AO15="Manual - annual", "Manual", IF(AO15="Automated - broken", "Automated by Staging Server", IF(AO15="Automated - daily", "Automated by Staging Server", ""))))))) -> None | AO15: Static | AX15: 42879 | AY15: =IF(DATEVALUE(AX15) < DATE(2014,7,1), 1, IF(DATEVALUE(AX15)<DATE(2015,7,1),2,IF(DATEVALUE(AX15)<DATE(2016,7,1),3,IF(DATEVALUE(AX15)<DATE(2017,7,1),4,IF(DATEVALUE(AX15)<DATE(2018,7,1),5,IF(DATEVALUE(AX15)<DATE(2019,7,1),6,IF(DATEVALUE(AX15) < DATE(2020,7,1), 7, IF(DATEVALUE(AX15) < DATE(2021,7,1), 8, IF(DATEVALUE(AX15) < DATE(2022,7,1), 9, IF(DATEVALUE(AX15) < DATE(2023,7,1), 10, IF(DATEVALUE(AX15) < DATE(2024,7,1), 11,IF(DATEVALUE(AX15) < DATE(2025,7,1),12,0)))))))))))) -> 4 | AZ15: =HYPERLINK("https://data.colorado.gov/Agriculture/Farmers-Markets-in-Colorado-2017/ms6b-y4xc","ms6b-y4xc") -> ms6b-y4xc | BA15: =HYPERLINK("https://data.colorado.gov/Agriculture/Farmers-Markets-in-Colorado-2017/ms6b-y4xc","ms6b-y4xc") -> ms6b-y4xc | BF15: =IF(AND(MONTH(AX15)>=7,MONTH(AX15)<=9), 1, IF(AND(MONTH(AX15)>=9,MONTH(AX15)<=12), 2, IF(AND(MONTH(AX15)>=1,MONTH(AX15)<=3), 3, IF(AND(MONTH(AX15)>=4,MONTH(AX15)<=6), 4)))) -> 4 | BG15: =LEFT(XLOOKUP(AZ15, cimAllData!$B$2:B1014, cimAllData!$F$2:$F1014), 10) -> #REF!
A16: Grocery Stores in Grand Junction Colorado | B16: Locations of grocery stores in the Grand Junction region, Colorado. | C16: Business | D16: bic, grocery, groceries, store, stores, food, food stores, locations, grand, junction, grand junction, gocodecolorado, mesa, mesa county, city, business, food desert, pantry, bank | E16: Business | F16: Creative Commons 1.0 Universal (Public Domain Dedication) | G16: City of Grand Junction | H16: =IFERROR(G16&" - "&INDEX(Taxonomy!N:N,MATCH(G16,Taxonomy!M:M,0)),G16) -> City of Grand Junction | I16: https://arcgis-app.gjcity.org/Business%20Map%20External/ | J16: CDOS | K16: =IFERROR(J16&" - "&INDEX(Taxonomy!N:N,MATCH(J16,Taxonomy!M:M,0)), J16) -> CDOS | L16: http://www.gjcity.org/Maps/ | M16: https://arcgis-app.gjcity.org/arcgis/rest/services/BusinessMap_external_MIL1/MapServer | N16: Jackson Trappett | Q16: Vector Point | S16: City of Grand Junction | X16: objectid,coname,city,state,zip | AA16: Locations of grocery stores in the Grand Junction region, Colorado including zip, city, and point coordinates. | AC16: https://arcgis-app.gjcity.org/arcgis/rest/services/BusinessMap_external_MIL1/MapServer/1/metadata | AK16: =IF(AO16="Static", "None", IF(AO16="Manual - monthly", "4th of month", IF(AO16="Automated - weekly", "Tuesday after 12AM", IF(AO16="Automated - monthly", "4th of month", IF(AO16="Manual - annual", "Annually", IF(AO16="Automated - broken", "Automation in progress", IF(AO16="Automated - daily", "Every day after midnight", ""))))))) -> 4th of month | AL16: Automated on Socrata by BIC | AN16: Last Updated 1/15/2020 | AO16: Automated - monthly | AP16: 22 | AS16: The name and location of the grocery store including city, zip, and coordinates. | AV16: 6 kb | AX16: 43794 | AY16: =IF(DATEVALUE(AX16) < DATE(2014,7,1), 1, IF(DATEVALUE(AX16)<DATE(2015,7,1),2,IF(DATEVALUE(AX16)<DATE(2016,7,1),3,IF(DATEVALUE(AX16)<DATE(2017,7,1),4,IF(DATEVALUE(AX16)<DATE(2018,7,1),5,IF(DATEVALUE(AX16)<DATE(2019,7,1),6,IF(DATEVALUE(AX16) < DATE(2020,7,1), 7, IF(DATEVALUE(AX16) < DATE(2021,7,1), 8, IF(DATEVALUE(AX16) < DATE(2022,7,1), 9, IF(DATEVALUE(AX16) < DATE(2023,7,1), 10, IF(DATEVALUE(AX16) < DATE(2024,7,1), 11,IF(DATEVALUE(AX16) < DATE(2025,7,1),12,0)))))))))))) -> 7 | AZ16: renj-ri3v | BA16: renj-ri3v | BF16: =IF(AND(MONTH(AX16)>=7,MONTH(AX16)<=9), 1, IF(AND(MONTH(AX16)>=9,MONTH(AX16)<=12), 2, IF(AND(MONTH(AX16)>=1,MONTH(AX16)<=3), 3, IF(AND(MONTH(AX16)>=4,MONTH(AX16)<=6), 4)))) -> 2 | BG16: =LEFT(XLOOKUP(AZ16, cimAllData!$B$2:B1015, cimAllData!$F$2:$F1015), 10) -> #REF!
A17: Highway Mileposts in Colorado | B17: Mileposts (or mile markers) along highways and their locations collection during GPS mapping efforts in the early 2000s from the Colorado Department of Transportation (CDOT). | C17: Transportation | D17: bic, gocodecolorado, colorado, cdot, colorado department of transportation, mileposts, mile markers, highway, location, transportation, gis | E17: Road Attributes | F17: Public Domain | G17: CDOT | H17: =IFERROR(G17&" - "&INDEX(Taxonomy!N:N,MATCH(G17,Taxonomy!M:M,0)),G17) -> CDOT | I17: http://dtdapps.coloradodot.info/staticdata/Downloads/StateGeoData/Mileposts.zip | J17: CDOT | K17: =IFERROR(J17&" - "&INDEX(Taxonomy!N:N,MATCH(J17,Taxonomy!M:M,0)), J17) -> CDOT | L17: https://www.codot.gov/ | M17: http://dtdapps.coloradodot.info/otis/catalog | N17: not public | O17: not public | Q17: Vector point | S17: State | X17: collector, comments, datafile, date, patrol, ref_pt, road_type, route, section | Y17: 09/11/2000 | Z17: 09/02/2004 | AA17: Colorado Highway and Frontage road milepost locations. Mileposts are locations of milepost (mile marker) locations alongside CDOT highways, collected during GPS mapping efforts in the early 2000s. MIleposts differ from milepoints in that milepoints represent the location along CDOT highways where that highway’s linear reference system indicates a whole number reference point (such as 57.000). Therefore, mileposts are not necessarily found at exactly at milepoints. Also includes collection date of point, route ID and some GPS locations. | AJ17: NAD83/UTM zone 13N | AK17: =IF(AO17="Static", "None", IF(AO17="Manual - monthly", "4th of month", IF(AO17="Automated - weekly", "Tuesday after 12AM", IF(AO17="Automated - monthly", "4th of month", IF(AO17="Manual - annual", "Annually", IF(AO17="Automated - broken", "Automation in progress", IF(AO17="Automated - daily", "Every day after midnight", ""))))))) -> 4th of month | AL17: =IF(AO17="Static", "None", IF(AO17="Manual - monthly", "Manual", IF(AO17="Automated - weekly", "Automated by Staging Server", IF(AO17="Automated - monthly", "Automated by Staging Server", IF(AO17="Manual - annual", "Manual", IF(AO17="Automated - broken", "Automated by Staging Server", IF(AO17="Automated - daily", "Automated by Staging Server", ""))))))) -> Automated by Staging Server | AO17: Automated - monthly | AP17: 11766 | AS17: Highway and frontage road milepost locations, route, and road type | AT17: 11767 | AU17: 7 | AX17: 42011 | AY17: =IF(DATEVALUE(AX17) < DATE(2014,7,1), 1, IF(DATEVALUE(AX17)<DATE(2015,7,1),2,IF(DATEVALUE(AX17)<DATE(2016,7,1),3,IF(DATEVALUE(AX17)<DATE(2017,7,1),4,IF(DATEVALUE(AX17)<DATE(2018,7,1),5,IF(DATEVALUE(AX17)<DATE(2019,7,1),6,IF(DATEVALUE(AX17) < DATE(2020,7,1), 7, IF(DATEVALUE(AX17) < DATE(2021,7,1), 8, IF(DATEVALUE(AX17) < DATE(2022,7,1), 9, IF(DATEVALUE(AX17) < DATE(2023,7,1), 10, IF(DATEVALUE(AX17) < DATE(2024,7,1), 11,IF(DATEVALUE(AX17) < DATE(2025,7,1),12,0)))))))))))) -> 2 | AZ17: =HYPERLINK("https://data.colorado.gov/Transportation/Colorado-Highway-Mileposts-GPS/trm9-dm4m","trm9-dm4m") -> trm9-dm4m | BA17: =HYPERLINK("https://dev.socrata.com/foundry/data.colorado.gov/2ivx-wb7h","2ivx-wb7h") -> 2ivx-wb7h | BB17: =HYPERLINK("https://data.colorado.gov/Transportation/Colorado-Highway-Mileposts-GPS/trm9-dm4m","trm9-dm4m") -> trm9-dm4m | BC17: WGS84 | BD17: NOTE: To maintain source projection, select “Export Original” from export menu. To display on the web, export using any other option. | BE17: Joinable to: Highway Milepoints in Colorado based on "ref_pt" | BF17: =IF(AND(MONTH(AX17)>=7,MONTH(AX17)<=9), 1, IF(AND(MONTH(AX17)>=9,MONTH(AX17)<=12), 2, IF(AND(MONTH(AX17)>=1,MONTH(AX17)<=3), 3, IF(AND(MONTH(AX17)>=4,MONTH(AX17)<=6), 4)))) -> 3 | BG17: =LEFT(XLOOKUP(AZ17, cimAllData!$B$2:B1016, cimAllData!$F$2:$F1016), 10) -> #REF! | BI17: Gary Aucott | BJ17: GIS Support Unit Manager | BK17: 303-512-4444 | BL17: gary.aucott@state.co.us | BM17: Gary Aucott | BN17: GIS Support Unit Manager | BO17: 303-512-4444 | BP17: gary.aucott@state.co.us | BQ17: Gary Aucott | BR17: gary.aucott@state.co.us
A18: Highway Routes in Colorado | B18: Route locations, segment lengths and route identifiers, from the Colorado Department of Transportation (CDOT). | C18: Transportation | D18: bic, gocodecolorado, colorado, cdot, colorado department of transportation, highway, roads, transportation, routes, length, gis | E18: Road Attributes | F18: Public Domain | G18: CDOT | H18: =IFERROR(G18&" - "&INDEX(Taxonomy!N:N,MATCH(G18,Taxonomy!M:M,0)),G18) -> CDOT | I18: http://dtdapps.coloradodot.info/staticdata/Downloads/StateGeoData/Routes.zip | J18: CDOT | K18: =IFERROR(J18&" - "&INDEX(Taxonomy!N:N,MATCH(J18,Taxonomy!M:M,0)), J18) -> CDOT | L18: https://www.codot.gov/ | M18: http://dtdapps.coloradodot.info/otis/catalog | N18: not public | O18: not public | Q18: Vector line | S18: State | X18: route, shape_len | AA18: Segment lengths and route identifiers for all routes in Colorado. CDOT defines routes by the number designating the State Route, including a section identifier designated by a letter for the State database. | AJ18: NAD83/UTM zone 13N | AK18: =IF(AO18="Static", "None", IF(AO18="Manual - monthly", "4th of month", IF(AO18="Automated - weekly", "Tuesday after 12AM", IF(AO18="Automated - monthly", "4th of month", IF(AO18="Manual - annual", "Annually", IF(AO18="Automated - broken", "Automation in progress", IF(AO18="Automated - daily", "Every day after midnight", ""))))))) -> 4th of month | AL18: =IF(AO18="Static", "None", IF(AO18="Manual - monthly", "Manual", IF(AO18="Automated - weekly", "Automated by Staging Server", IF(AO18="Automated - monthly", "Automated by Staging Server", IF(AO18="Manual - annual", "Manual", IF(AO18="Automated - broken", "Automated by Staging Server", IF(AO18="Automated - daily", "Automated by Staging Server", ""))))))) -> Automated by Staging Server | AO18: Automated - monthly | AP18: 181 | AS18: Segment lengths and route identifiers highway routes | AT18: 291 | AU18: 2 | AX18: 42013 | AY18: =IF(DATEVALUE(AX18) < DATE(2014,7,1), 1, IF(DATEVALUE(AX18)<DATE(2015,7,1),2,IF(DATEVALUE(AX18)<DATE(2016,7,1),3,IF(DATEVALUE(AX18)<DATE(2017,7,1),4,IF(DATEVALUE(AX18)<DATE(2018,7,1),5,IF(DATEVALUE(AX18)<DATE(2019,7,1),6,IF(DATEVALUE(AX18) < DATE(2020,7,1), 7, IF(DATEVALUE(AX18) < DATE(2021,7,1), 8, IF(DATEVALUE(AX18) < DATE(2022,7,1), 9, IF(DATEVALUE(AX18) < DATE(2023,7,1), 10, IF(DATEVALUE(AX18) < DATE(2024,7,1), 11,IF(DATEVALUE(AX18) < DATE(2025,7,1),12,0)))))))))))) -> 2 | AZ18: =HYPERLINK("https://data.colorado.gov/Transportation/Colorado-Highway-Routes/xs2v-uzeg","xs2v-uzeg") -> xs2v-uzeg | BA18: =HYPERLINK("https://dev.socrata.com/foundry/data.colorado.gov/i7qk-ahka","i7qk-ahka") -> i7qk-ahka | BB18: =HYPERLINK("https://data.colorado.gov/Transportation/Colorado-Highway-Routes/xs2v-uzeg","xs2v-uzeg") -> xs2v-uzeg | BC18: WGS84 | BD18: NOTE: To maintain source projection, select “Export Original” from export menu. To display on the web, export using any other option. | BE18: Related to: Highways in Colorado | BF18: =IF(AND(MONTH(AX18)>=7,MONTH(AX18)<=9), 1, IF(AND(MONTH(AX18)>=9,MONTH(AX18)<=12), 2, IF(AND(MONTH(AX18)>=1,MONTH(AX18)<=3), 3, IF(AND(MONTH(AX18)>=4,MONTH(AX18)<=6), 4)))) -> 3 | BG18: =LEFT(XLOOKUP(AZ18, cimAllData!$B$2:B1017, cimAllData!$F$2:$F1017), 10) -> #REF! | BI18: Gary Aucott | BJ18: GIS Support Unit Manager | BK18: 303-512-4444 | BL18: gary.aucott@state.co.us | BM18: Gary Aucott | BN18: GIS Support Unit Manager | BO18: 303-512-4444 | BP18: gary.aucott@state.co.us | BQ18: Gary Aucott | BR18: gary.aucott@state.co.us
A19: Local Roads in Colorado | B19: Local Roads are functionally identified as local and excludes major roads or highways. Each road is segmented with a to and from description. The direction, length, type (paved/dirt), width (in feet), local route name and id, number of lanes, one/two-way bridges, average daily traffic counts, locations of count stations, if it is congested, if maintenance is under shared jurisdiction and the year it was built or last updated from the Colorado Department of Transportation (CDOT). | C19: Transportation | D19: bic, gocodecolorado, colorado, cdot, colorado department of transportation, transportation, public roads, roads, local roads, city, county, location, urban roads, rural roads, congestion, gis | E19: Road Attributes | F19: Public Domain | G19: CDOT | H19: =IFERROR(G19&" - "&INDEX(Taxonomy!N:N,MATCH(G19,Taxonomy!M:M,0)),G19) -> CDOT | I19: http://dtdapps.coloradodot.info/staticdata/Downloads/StateGeoData/LocalRoads.zip | J19: CDOT | K19: =IFERROR(J19&" - "&INDEX(Taxonomy!N:N,MATCH(J19,Taxonomy!M:M,0)), J19) -> CDOT | L19: https://www.codot.gov/ | M19: http://dtdapps.coloradodot.info/otis/catalog | N19: not public | O19: not public | Q19: Vector line | S19: State | X19: aadt, aadtderiv, aadtyr, adminclass, alias, builtyr, congested, countstati, cr_id, descriptio, fips, fipscounty, forestrout, from_descr, frommeas, funcclassi, fund_id, gis_id, govlevel, hpmsid, jursplit, lrs_bgn, lrs_end, lrsroute, map_num, map_text, nhsdesig, operation, population, priiri, pripsi, prisurfwd, prithrulnw, route, routename, seg_length, segmdir, segmid, shape_len, shape_st_1, shape_stle, specialsys, surf_type, surfname, thrulnqty, thrulnwd, to_descr, tomeas, urban | AA19: Public roads under local (city/county) jurisdiction that are functionally identified as local. Does not contain major roads or highways. Each road is segmented with a to and from description. The direction, length, type (paved/dirt), width (in feet), local route name and id, number of lanes, one/two-way bridges, average daily traffic counts, locations of count stations, if it is congested, if maintenance is under shared jurisdiction and the year it was built or last updated. Political jurisdictions for each segment include FIPS County codes, CDOT Administrative Zones, primary responsible Government Level (designated by Federal Highway Act), whether a segment is urban or rural (designated by the Census), whether it has National Highway Designation, if it is a designated Forest Route, and if it is eligible for local or special funding. | AJ19: NAD83/UTM zone 13N | AK19: =IF(AO19="Static", "None", IF(AO19="Manual - monthly", "4th of month", IF(AO19="Automated - weekly", "Tuesday after 12AM", IF(AO19="Automated - monthly", "4th of month", IF(AO19="Manual - annual", "Annually", IF(AO19="Automated - broken", "Automation in progress", IF(AO19="Automated - daily", "Every day after midnight", ""))))))) -> 4th of month | AL19: =IF(AO19="Static", "None", IF(AO19="Manual - monthly", "Manual", IF(AO19="Automated - weekly", "Automated by Staging Server", IF(AO19="Automated - monthly", "Automated by Staging Server", IF(AO19="Manual - annual", "Manual", IF(AO19="Automated - broken", "Automated by Staging Server", IF(AO19="Automated - daily", "Automated by Staging Server", ""))))))) -> Automated by Staging Server | AO19: Automated - monthly | AP19: 162814 | AS19: Local roads name, length, location, congestion, and year built | AT19: 164361 | AU19: 42 | AX19: 42017 | AY19: =IF(DATEVALUE(AX19) < DATE(2014,7,1), 1, IF(DATEVALUE(AX19)<DATE(2015,7,1),2,IF(DATEVALUE(AX19)<DATE(2016,7,1),3,IF(DATEVALUE(AX19)<DATE(2017,7,1),4,IF(DATEVALUE(AX19)<DATE(2018,7,1),5,IF(DATEVALUE(AX19)<DATE(2019,7,1),6,IF(DATEVALUE(AX19) < DATE(2020,7,1), 7, IF(DATEVALUE(AX19) < DATE(2021,7,1), 8, IF(DATEVALUE(AX19) < DATE(2022,7,1), 9, IF(DATEVALUE(AX19) < DATE(2023,7,1), 10, IF(DATEVALUE(AX19) < DATE(2024,7,1), 11,IF(DATEVALUE(AX19) < DATE(2025,7,1),12,0)))))))))))) -> 2 | AZ19: =HYPERLINK("https://data.colorado.gov/Transportation/Colorado-Local-Roads/qvrk-xsmj","qvrk-xsmj") -> qvrk-xsmj | BA19: =HYPERLINK("https://dev.socrata.com/foundry/data.colorado.gov/nxhx-5jh3","nxhx-5jh3") -> nxhx-5jh3 | BB19: =HYPERLINK("https://data.colorado.gov/Transportation/Colorado-Local-Roads/qvrk-xsmj","qvrk-xsmj") -> qvrk-xsmj | BC19: WGS84 | BD19: NOTE: To maintain source projection, select “Export Original” from export menu. To display on the web, export using any other option. | BE19: Related to: Highways in Colorado, Major Roads in Colorado | BF19: =IF(AND(MONTH(AX19)>=7,MONTH(AX19)<=9), 1, IF(AND(MONTH(AX19)>=9,MONTH(AX19)<=12), 2, IF(AND(MONTH(AX19)>=1,MONTH(AX19)<=3), 3, IF(AND(MONTH(AX19)>=4,MONTH(AX19)<=6), 4)))) -> 3 | BG19: =LEFT(XLOOKUP(AZ19, cimAllData!$B$2:B1018, cimAllData!$F$2:$F1018), 10) -> #REF! | BI19: Gary Aucott | BJ19: GIS Support Unit Manager | BK19: 303-512-4444 | BL19: gary.aucott@state.co.us | BM19: Gary Aucott | BN19: GIS Support Unit Manager | BO19: 303-512-4444 | BP19: gary.aucott@state.co.us | BQ19: Gary Aucott | BR19: gary.aucott@state.co.us
A20: Metro Districts in Colorado | B20: Aggregated from thousands of local jurisdictions by the Colorado Department of Local Affairs Demography office. Many of the district boundaries were created from scanned drawings or digitized PDFs, and therefore no guarantee of accuracy can be made for the data. | C20: Local Aggregation | D20: bic, gocodecolorado, colorado, dola, department of local affairs, districts, special districts, boundaries, metropolitan, metro, gis | E20: Special Districts | F20: Public Domain | G20: DOLA | H20: =IFERROR(G20&" - "&INDEX(Taxonomy!N:N,MATCH(G20,Taxonomy!M:M,0)),G20) -> DOLA | I20: https://storage.googleapis.com/co-publicdata/dlmetro.zip | J20: DOLA | K20: =IFERROR(J20&" - "&INDEX(Taxonomy!N:N,MATCH(J20,Taxonomy!M:M,0)), J20) -> DOLA | L20: https://www.colorado.gov/dola | M20: https://demography.dola.colorado.gov/gis/ | N20: not public | O20: not public | Q20: Vector polygon | S20: State | T20: Digitized from scanned images and pdfs | U20: vectorized from maps | V20: aggregated in GIS | X20: alt_addres, lgid, lgname, lgstatusid, lgtypeid, mail_addre, mail_city, mail_state, mail_zip, prev_name, source, url | AA20: Colorado contains thousands of governmental entities referred to as ’special districts’. Currently there is not a single authoritative source for boundary and/or GIS information of these districts. This project attempts to fill that void. Please note the disclaimer. Since many of these district boundaries trace their origin to scanned drawings or digitized PDFs we can not guarantee the accuracy of the data, and as such, these boundaries should not be seen as an authoritative source of information. The creator (DOLA) and contributors to this project do not guarantee the accuracy of any information presented, are not liable for any errors or omissions and are not responsible for determining fitness for use, either in this map or in its associated data. This data should not be considered an authoritative source of information. | AC20: https://docs.google.com/spreadsheets/d/1gaOjeXlLzQankggbhtrQq3HDEPfwwiXiPeSZrP6FjOs/edit?usp=sharing | AI20: not yet verified | AJ20: WGS 84, EPSG:4326 | AK20: =IF(AO20="Static", "None", IF(AO20="Manual - monthly", "4th of month", IF(AO20="Automated - weekly", "Tuesday after 12AM", IF(AO20="Automated - monthly", "4th of month", IF(AO20="Manual - annual", "Annually", IF(AO20="Automated - broken", "Automation in progress", IF(AO20="Automated - daily", "Every day after midnight", ""))))))) -> 4th of month | AL20: =IF(AO20="Static", "None", IF(AO20="Manual - monthly", "Manual", IF(AO20="Automated - weekly", "Automated by Staging Server", IF(AO20="Automated - monthly", "Automated by Staging Server", IF(AO20="Manual - annual", "Manual", IF(AO20="Automated - broken", "Automated by Staging Server", IF(AO20="Automated - daily", "Automated by Staging Server", ""))))))) -> Automated by Staging Server | AO20: Automated - monthly | AP20: 1299 | AS20: Metro district location, name, and contact information | AT20: 1300 | AU20: 14 | AX20: 42374 | AY20: =IF(DATEVALUE(AX20) < DATE(2014,7,1), 1, IF(DATEVALUE(AX20)<DATE(2015,7,1),2,IF(DATEVALUE(AX20)<DATE(2016,7,1),3,IF(DATEVALUE(AX20)<DATE(2017,7,1),4,IF(DATEVALUE(AX20)<DATE(2018,7,1),5,IF(DATEVALUE(AX20)<DATE(2019,7,1),6,IF(DATEVALUE(AX20) < DATE(2020,7,1), 7, IF(DATEVALUE(AX20) < DATE(2021,7,1), 8, IF(DATEVALUE(AX20) < DATE(2022,7,1), 9, IF(DATEVALUE(AX20) < DATE(2023,7,1), 10, IF(DATEVALUE(AX20) < DATE(2024,7,1), 11,IF(DATEVALUE(AX20) < DATE(2025,7,1),12,0)))))))))))) -> 3 | AZ20: =HYPERLINK("https://data.colorado.gov/Government/Metropolitan-Districts-of-Colorado/knbf-ggf2","knbf-ggf2") -> knbf-ggf2 | BA20: =HYPERLINK("https://dev.socrata.com/foundry/data.colorado.gov/6mdp-xw2u","6mdp-xw2u") -> 6mdp-xw2u | BB20: =HYPERLINK("https://data.colorado.gov/Government/Metropolitan-Districts-of-Colorado/knbf-ggf2","knbf-ggf2") -> knbf-ggf2 | BC20: WGS84 | BD20: NOTE: To maintain source projection, select “Export Original” from export menu. To display on the web, export using any other option. | BE20: Related to: All Special Districts in Colorado, Cemetary Districts in Colorado, Fire Districts in Colorado, Hospital Districts in Colorado, Library Districts in Colorado, Parks and Rec Districts in Colorado, School Districts in Colorado, Soil Districts in Colorado, Water and Sanitation Districts in Colorado | BF20: =IF(AND(MONTH(AX20)>=7,MONTH(AX20)<=9), 1, IF(AND(MONTH(AX20)>=9,MONTH(AX20)<=12), 2, IF(AND(MONTH(AX20)>=1,MONTH(AX20)<=3), 3, IF(AND(MONTH(AX20)>=4,MONTH(AX20)<=6), 4)))) -> 3 | BG20: =LEFT(XLOOKUP(AZ20, cimAllData!$B$2:B1019, cimAllData!$F$2:$F1019), 10) -> #REF! | BI20: Elizabeth Garner | BJ20: State Demographer | BK20: 303-864-7753 | BL20: Elizabeth.Garner@state.co.us | BM20: Todd Bleess | BN20: GIS Developer | BO20: 303-864-7754 | BP20: todd.bleess@state.co.us
A21: Subcontractors for Lobbyists in Colorado | B21: Information for each lobbyist that hires another lobbyist or lobbying business (subcontractor) along with total gross income paid ito the subcontractor in the given report month for the State of Colorado dating back to 2002 provided by the Colorado Department of State (CDOS). | C21: Lobbyist | D21: bic, gocodecolorado, colorado, sos, secretary of statelobbyists, subcontractors, income, gross income | E21: Lobbyist | F21: Public Domain | G21: CDOS | H21: =IFERROR(G21&" - "&INDEX(Taxonomy!N:N,MATCH(G21,Taxonomy!M:M,0)),G21) -> CDOS | J21: CDOS | K21: =IFERROR(J21&" - "&INDEX(Taxonomy!N:N,MATCH(J21,Taxonomy!M:M,0)), J21) -> CDOS | L21: https://www.sos.state.co.us/ | M21: https://www.sos.state.co.us/pubs/lobby/FAQs/professional.html | N21: not public | O21: not public | Q21: Tabular | S21: State | X21: lobbyistlastname, lobbyistfirstname, lobbyistaddress0, lobbyistaddress1, lobbyistcity, lobbyiststate, lobbyistzip, primarylobbyistid, annuallobbyistregistrationid, subcontractorsource, subcontractoraddressline0, subcontractoraddressline1, subcontractorcity, subcontractorstate, subcontractorzip, incomeamountreceived, amountpaidtosubcontractor, incomereceiptdate, subcontractorlastname, subcontractorfirstname, reportmonth, fiscalyear, reportduedate | Y21: 04/01/1996 | Z21: 01/16/2018 | AA21: Information for each lobbyist that hires another lobbyist or lobbying business (subcontractor) along with total gross income paid to the subcontractor in the given report month, for the State of Colorado dating back to 2002. Subcontractors are always another lobbyist or lobbying firm, and have to be a registered lobbyist in the current fiscal year. State Liaisons as registered lobbyists are differentiated from professional lobbyists in that they cannot subcontract to other lobbyists. Information related to the bill and position of the subcontractor is reported along with the client of the primary lobbyist in the “Bill Information and Position with Income of Lobbyist in Colorado” table. The primaryLobbyistID field is the number is assigned when the lobbyist registers with the state, and the first four numbers are the year of original registration. The annual lobbyist registration identification number is updated when they register in a current fiscal year, and the first four numbers reflect status of the lobbyist when registering in a current fiscal year (for example, if they were registered in 2015, but did not update their registration in 2016, then the registration id would remain 2015 until they register in a new fiscal year). The data is updated as necessary to the main lobbyist online system via manual entry, however the updates to the Colorado Information Marketplace is only done weekly, every Monday night. Data goes back to 1995, but in 2002 a mandate established that the secretary of state transition to an online system. Then in 2010 Senate Bill 10-87, among other major changes, shifted the lobbyist registration and disclosure periods to the state fiscal year rather than the calendar year. When the data is entered into the system by the lobbyists, subcontractor lobbyists report who their primary lobbyist is. Primary lobbyists do not report who their subcontractors are. | AK21: =IF(AO21="Static", "None", IF(AO21="Manual - monthly", "4th of month", IF(AO21="Automated - weekly", "Tuesday after 12AM", IF(AO21="Automated - monthly", "4th of month", IF(AO21="Manual - annual", "Annually", IF(AO21="Automated - broken", "Automation in progress", IF(AO21="Automated - daily", "Every day after midnight", ""))))))) -> None | AL21: =IF(AO21="Static", "None", IF(AO21="Manual - monthly", "Manual", IF(AO21="Automated - weekly", "Automated by Staging Server", IF(AO21="Automated - monthly", "Automated by Staging Server", IF(AO21="Manual - annual", "Manual", IF(AO21="Automated - broken", "Automated by Staging Server", IF(AO21="Automated - daily", "Automated by Staging Server", ""))))))) -> None | AO21: Static | AS21: Lobbyist and associated subcontractor name and contact, income received by lobbyist, and amount paid to subcontractor | AT21: 6302 | AX21: 42547 | AY21: =IF(DATEVALUE(AX21) < DATE(2014,7,1), 1, IF(DATEVALUE(AX21)<DATE(2015,7,1),2,IF(DATEVALUE(AX21)<DATE(2016,7,1),3,IF(DATEVALUE(AX21)<DATE(2017,7,1),4,IF(DATEVALUE(AX21)<DATE(2018,7,1),5,IF(DATEVALUE(AX21)<DATE(2019,7,1),6,IF(DATEVALUE(AX21) < DATE(2020,7,1), 7, IF(DATEVALUE(AX21) < DATE(2021,7,1), 8, IF(DATEVALUE(AX21) < DATE(2022,7,1), 9, IF(DATEVALUE(AX21) < DATE(2023,7,1), 10, IF(DATEVALUE(AX21) < DATE(2024,7,1), 11,IF(DATEVALUE(AX21) < DATE(2025,7,1),12,0)))))))))))) -> 3 | AZ21: =HYPERLINK("https://data.colorado.gov/Legislative/Subcontractors-for-Lobbyists-in-Colorado/gcmk-9nwy","gcmk-9nwy") -> gcmk-9nwy | BA21: =HYPERLINK("https://data.colorado.gov/resource/37vx-jsnr.json","37vx-jsnr") -> 37vx-jsnr | BE21: Joinable to: Bill Information and Position with Income of Lobbyist in Colorado, Characterization of Lobbyist Clients in Colorado, Directory of Lobbyist Clients in Colorado, Directory of Lobbyists in Colorado, Expenses for Lobbyists in Colorado based on "primaryLobbyistId" | BF21: =IF(AND(MONTH(AX21)>=7,MONTH(AX21)<=9), 1, IF(AND(MONTH(AX21)>=9,MONTH(AX21)<=12), 2, IF(AND(MONTH(AX21)>=1,MONTH(AX21)<=3), 3, IF(AND(MONTH(AX21)>=4,MONTH(AX21)<=6), 4)))) -> 4 | BG21: =LEFT(XLOOKUP(AZ21, cimAllData!$B$2:B1020, cimAllData!$F$2:$F1020), 10) -> #REF! | BJ21: BIC Program Manager | BM21: Angela Lawson | BN21: Lobbyist Registration Program Manager | BO21: 303-894-2200, ext. 6304 | BP21: a.lawson@sos.state.co.us | BQ21: Sebbie Coleman | BR21: sebbie.coleman@sos.state.co.us
A22: Transparency Online Project (TOPS) - State Government Revenue and Expenditures in Colorado | B22: Revenue and Expenditures for Colorado State Governmental departments provided by the Department of Personnel & Administration and the Office of the State Controller. Documentation can be found in the long description of the dataset. | C22: Government | D22: bic, gocodecolorado, dpa, public, affairs, expenditures, revenue, vendors, vend, business, BIC, business, transparency, tops, gov | E22: Executive | F22: Public Domain | G22: DPA | H22: =IFERROR(G22&" - "&INDEX(Taxonomy!N:N,MATCH(G22,Taxonomy!M:M,0)),G22) -> DPA | I22: https://apps.colorado.gov/apps/oit/transparency/index.html | J22: DPA | K22: =IFERROR(J22&" - "&INDEX(Taxonomy!N:N,MATCH(J22,Taxonomy!M:M,0)), J22) -> DPA | L22: https://dpa.colorado.gov/ | M22: https://dpa.colorado.gov/ | N22: John McIntosh | O22: 303-866-6623 | P22: CORE - Colorado Operations Resource Engine | Q22: Tabular | R22: Record level transaction activity | S22: State | T22: Daily data extract from The State of Colorado financial ledger | U22: Daily data extract with a two day lag | V22: Business Objects report running against The State's ERP system | W22: 43937 | X22: Entity Name, Fiscal Year, Fiscal Period, Journal Date, Type, Vendor Legal Name - Not Redacted, Vendor Invoice, Commodity Description, Cabinet, Department, Unit, Fund Category, Fund, Appropriation Class, Appropriation, GCF, Major Program, Program, CFDA Number, PPC Federal Catalog Agency-Suffix, Statement, Statement Line, Account Category, Account Name, Jrnl Doc Code, Jrnl Doc (Code,Dept,ID,Vers), Record ID, Amount | Y22: 2015 | Z22: 2022 | AA22: User Guide: https://github.com/GoCodeColorado/GoCodeColorado-kbase-public/blob/master/Data/CDPA%20Transparency%20Online%20Project%20(TOPS).md | AK22: =IF(AO22="Static", "None", IF(AO22="Manual - monthly", "4th of month", IF(AO22="Automated - weekly", "Tuesday after 12AM", IF(AO22="Automated - monthly", "4th of month", IF(AO22="Manual - annual", "Annually", IF(AO22="Automated - broken", "Automation in progress", IF(AO22="Automated - daily", "Every day after midnight", ""))))))) -> Tuesday after 12AM | AL22: =IF(AO22="Static", "None", IF(AO22="Manual - monthly", "Manual", IF(AO22="Automated - weekly", "Automated by Staging Server", IF(AO22="Automated - monthly", "Automated by Staging Server", IF(AO22="Manual - annual", "Manual", IF(AO22="Automated - broken", "Automated by Staging Server", IF(AO22="Automated - daily", "Automated by Staging Server", ""))))))) -> Automated by Staging Server | AM22: Annually | AO22: Automated - weekly | AP22: 44734744 | AS22: Revenue and Expenditure amounts and departmental and other funding attributes context for a given vendor job in a given period of time. | AT22: 44734744 | AU22: 28 | AV22: 31 gb | AX22: 43937 | AY22: =IF(DATEVALUE(AX22) < DATE(2014,7,1), 1, IF(DATEVALUE(AX22)<DATE(2015,7,1),2,IF(DATEVALUE(AX22)<DATE(2016,7,1),3,IF(DATEVALUE(AX22)<DATE(2017,7,1),4,IF(DATEVALUE(AX22)<DATE(2018,7,1),5,IF(DATEVALUE(AX22)<DATE(2019,7,1),6,IF(DATEVALUE(AX22) < DATE(2020,7,1), 7, IF(DATEVALUE(AX22) < DATE(2021,7,1), 8, IF(DATEVALUE(AX22) < DATE(2022,7,1), 9, IF(DATEVALUE(AX22) < DATE(2023,7,1), 10, IF(DATEVALUE(AX22) < DATE(2024,7,1), 11,IF(DATEVALUE(AX22) < DATE(2025,7,1),12,0)))))))))))) -> 7 | AZ22: =HYPERLINK("https://data.colorado.gov/dataset/Colorado-State-Government-Departments-Expenses-and/rifs-n6ib","rifs-n6ib") -> rifs-n6ib | BA22: =HYPERLINK("https://data.colorado.gov/dataset/Colorado-State-Government-Departments-Expenses-and/rifs-n6ib","rifs-n6ib") -> rifs-n6ib | BF22: =IF(AND(MONTH(AX22)>=7,MONTH(AX22)<=9), 1, IF(AND(MONTH(AX22)>=9,MONTH(AX22)<=12), 2, IF(AND(MONTH(AX22)>=1,MONTH(AX22)<=3), 3, IF(AND(MONTH(AX22)>=4,MONTH(AX22)<=6), 4)))) -> 4 | BG22: =LEFT(XLOOKUP(AZ22, cimAllData!$B$2:B1021, cimAllData!$F$2:$F1021), 10) -> #REF! | BI22: Paul Reynolds | BJ22: Financial Reporting Manager | BK22: 3038663468 | BL22: paul.reynolds@state.co.us | BN22: John Mcintosh
